{
  "lesson_meta": {
    "title": "கல்வி கண் போன்றது",
    "unit": "4",
    "grade": "3",
    "term": "t2",
    "subject": "tamil",
    "code": "tam_3_t2_l4"
  },
  "quiz": {
    "questions": [
      {
        "question": "ஊராட்சி மன்ற அலுவலகத்தில் கிராமசபைக் கூட்டம் நடைபெற்ற கிராமத்தின் பெயர் என்ன?",
        "options": [
          "பனையூர்",
          "விரியூர்",
          "களத்தூர்",
          "சிறுவூர்"
        ],
        "answer": 1,
        "explanation": "கதையின் தொடக்கத்தில், 'விரியூர் கிராமத்திலுள்ள ஊராட்சி மன்ற அலுவலகத்தில்...' என்று குறிப்பிடப்பட்டுள்ளது."
      },
      {
        "question": "கிராமசபைக் கூட்டத்திற்கு வந்திருந்தவர்களை வரவேற்றுப் பேசியவர் யார்?",
        "options": [
          "ஆசிரியர்",
          "கிராம நிர்வாக அலுவலர்",
          "ஊராட்சி மன்றத் தலைவர்",
          "அஞ்சல்காரர்"
        ],
        "answer": 2,
        "explanation": "ஊராட்சி மன்றத் தலைவர் கூட்டத்திற்கு வந்திருந்தவர்களை வரவேற்றுப் பேசினார் எனப் பாடத்தில் உள்ளது."
      },
      {
        "question": "அரசின் திட்டம் எதற்காக உதவித்தொகை வழங்குவதாக இருந்தது?",
        "options": [
          "வீடு கட்ட",
          "விவசாயம் செய்ய",
          "சிறுதொழில் தொடங்க",
          "மருத்துவச் செலவிற்கு"
        ],
        "answer": 2,
        "explanation": "சிறுதொழில் தொடங்குவதற்கான உதவித்தொகை வழங்கும் அரசின் திட்டம் குறித்துத் தலைவர் பேசினார்."
      },
      {
        "question": "கூட்டத்தில் தன்னுடைய பெயர் வருகிறதா என ஆவலோடு எதிர்பார்த்துக் கொண்டிருந்தவர் யார்?",
        "options": [
          "அஞ்சல்காரர்",
          "பொன்வண்ணன்",
          "பொன்வண்ணனின் மகன்",
          "ஊராட்சி மன்றத் தலைவர்"
        ],
        "answer": 1,
        "explanation": "பொன்வண்ணன் தன்னுடைய பெயர் வருகிறதா என ஆவலோடு எதிர்பார்த்துக் கொண்டிருந்தார்."
      },
      {
        "question": "பொன்வண்ணன் தலைவரிடம் சென்று என்ன கேட்டார்?",
        "options": [
          "எனக்கு ஏன் வேலை இல்லை?",
          "எனக்கு ஏன் உதவித்தொகை இல்லை?",
          "என் மகனுக்கு ஏன் பள்ளி சீருடை இல்லை?",
          "என் கடைக்கு ஏன் மின்சாரம் இல்லை?"
        ],
        "answer": 1,
        "explanation": "பண வசதியில்லாமல் துன்பப்படும் தனக்கு ஏன் உதவித்தொகை இல்லை என்று பொன்வண்ணன் தலைவரிடம் கேட்டார்."
      },
      {
        "question": "உதவித்தொகை தேவையோர்களுக்கான கூட்டம் பற்றிய தகவல் எவ்வாறு தெரிவிக்கப்பட்டது?",
        "options": [
          "தொலைபேசி மூலம்",
          "அஞ்சல் மூலம்",
          "தண்டோரா மூலம்",
          "செய்தித்தாள் மூலம்"
        ],
        "answer": 1,
        "explanation": "யாருக்கெல்லாம் பண உதவி தேவையோ, அவர்களுக்கான கூட்டம் பற்றி அஞ்சல் மூலம் தெரிவித்ததாகத் தலைவர் கூறினார்."
      },
      {
        "question": "பொன்வண்ணனுக்குக் கடிதத்தை வழங்கியவர் யார்?",
        "options": [
          "அஞ்சல்காரர்",
          "ஆசிரியர்",
          "தலைவர்",
          "அக்கம் பக்கத்தினர்"
        ],
        "answer": 0,
        "explanation": "போன வாரம் அஞ்சல்காரர் கொடுத்தார் என்று பொன்வண்ணன் கூறுகிறார்."
      },
      {
        "question": "அஞ்சல்காரர் கொடுத்த கடிதத்தைப் பொன்வண்ணன் ஏன் படிக்கவில்லை?",
        "options": [
          "நேரமில்லை என்பதால்",
          "கடிதம் தொலைந்துவிட்டதால்",
          "படிக்கத் தெரியாததால்",
          "பார்வைக் குறைபாட்டால்"
        ],
        "answer": 2,
        "explanation": "படிக்கத் தெரியாததால் கடிதத்தை அப்படியே வைத்துவிட்டதாகப் பொன்வண்ணன் கூறினார்."
      },
      {
        "question": "பொன்வண்ணனுக்குப் படிக்கத் தெரியாவிட்டாலும், வேறு யாருக்குப் படிக்கத் தெரியும் எனத் தலைவர் எண்ணினார்?",
        "options": [
          "அவரது மனைவிக்கு",
          "பள்ளியில் படிக்கும் அவரது மகனுக்கு",
          "அவரது நண்பருக்கு",
          "அவரது தம்பிக்கு"
        ],
        "answer": 1,
        "explanation": "பள்ளியிலே படிக்கும் உன் பையனுக்கு எப்படித் தெரியாமல் போகும் என்று தலைவர் கேட்டார்."
      },
      {
        "question": "பொன்வண்ணன் என்ன கடை வைத்திருந்தார்?",
        "options": [
          "மளிகைக் கடை",
          "தேநீர் கடை",
          "மிதிவண்டி பழுதுபார்க்கும் கடை",
          "துணிக்கடை"
        ],
        "answer": 2,
        "explanation": "நான் வைத்துள்ள மிதிவண்டி பழுதுபார்க்கும் கடையில் உதவி செய்வதற்காக... என்று பொன்வண்ணன் கூறுகிறார்."
      },
      {
        "question": "பொன்வண்ணனின் மகனுக்கு ஏன் சரியாக எழுதவும் படிக்கவும் தெரியாமல் போனது?",
        "options": [
          "பள்ளியில் ஆசிரியர்கள் சரியாகக் கற்பிக்காததால்",
          "கடை வேலையில் உதவி செய்ய அடிக்கடி விடுப்பு எடுத்ததால்",
          "பள்ளி வெகு தொலைவில் இருந்ததால்",
          "பாடப்புத்தகங்கள் இல்லாததால்"
        ],
        "answer": 1,
        "explanation": "கடையில் உதவி செய்வதற்காக அவனை அடிக்கடி பள்ளிக்கு விடுப்பு எடுக்கச் செய்ததால் அவனுக்குச் சரியாக எழுதவும் படிக்கவும் தெரியாமல் போய்விட்டது."
      },
      {
        "question": "பொன்வண்ணனின் மகன் அடிக்கடி விடுப்பு எடுப்பது குறித்து அவரிடம் கூறியது யார்?",
        "options": [
          "ஊராட்சி மன்றத் தலைவர்",
          "அஞ்சல்காரர்",
          "அவனுடைய ஆசிரியர்",
          "கிராம மக்கள்"
        ],
        "answer": 2,
        "explanation": "அவனுடைய ஆசிரியரும் இதைப்பற்றி என்னிடம் அடிக்கடி கூறி இருந்தார் என்று பொன்வண்ணன் நினைக்கிறார்."
      },
      {
        "question": "தன் மகனைப் படிக்கத் தெரியாதவனாக ஆக்கிவிட்டோமே எனப் பொன்வண்ணன் எவ்வாறு உணர்ந்தார்?",
        "options": [
          "மகிழ்ச்சியுடன்",
          "குற்ற உணர்வோடு",
          "கோபத்தோடு",
          "அலட்சியமாக"
        ],
        "answer": 1,
        "explanation": "பொன்வண்ணன் சற்றுக் குற்ற உணர்வோடு தலை குனிந்தார் எனப் பாடத்தில் உள்ளது."
      },
      {
        "question": "கதையின் முடிவில் பொன்வண்ணன் எடுத்த முடிவு என்ன?",
        "options": [
          "மகனை முழுநேரமாகக் கடையில் வேலை செய்ய வைப்பது",
          "வேலைக்காக இனி மகனைப் பள்ளியை விட்டு நிறுத்தாமல் தினமும் அனுப்புவது",
          "ஊராட்சி மன்றத் தலைவரிடம் சண்டையிடுவது",
          "மிதிவண்டி கடையை மூடிவிடுவது"
        ],
        "answer": 1,
        "explanation": "வேலைக்காக இனி நான் என் மகனைப் பள்ளியை விட்டு நிறுத்த மாட்டேன், தினமும் பள்ளிக்கு அனுப்புவேன் என்று எண்ணினார்."
      },
      {
        "question": "குழந்தைகளை வேலைக்கு அமர்த்துவது எத்தகைய செயல்?",
        "options": [
          "பொருளாதாரத்தை உயர்த்தும் செயல்",
          "சட்டப்படி குற்றமாகும்",
          "பெற்றோருக்கு உதவும் செயல்",
          "தவிர்க்க முடியாத செயல்"
        ],
        "answer": 1,
        "explanation": "அறிந்துகொள்வோம் பகுதியில், குழந்தைகளை வேலைக்கு அமர்த்துவது சட்டப்படி குற்றமாகும் என்று கூறப்பட்டுள்ளது."
      },
      {
        "question": "ஆண்டுதோறும் எந்த நாள் 'குழந்தைத்தொழிலாளர் ஒழிப்பு நாளாக' கடைப்பிடிக்கப்படுகிறது?",
        "options": [
          "ஜூன் 5",
          "அக்டோபர் 2",
          "ஜூன் 12",
          "நவம்பர் 14"
        ],
        "answer": 2,
        "explanation": "குழந்தைத்தொழிலாளர் ஒழிப்புநாள் ஆண்டுதோறும் ஜூன் 12 அன்று கடைப்பிடிக்கப்படுகிறது."
      },
      {
        "question": "'துன்பம்' என்ற சொல்லின் எதிர்ச்சொல் எது?",
        "options": [
          "துயரம்",
          "கவலை",
          "இன்பம்",
          "வருத்தம்"
        ],
        "answer": 2,
        "explanation": "துன்பம் என்பதற்கு எதிரான சொல் இன்பம் ஆகும். மற்றவை துன்பத்தைக் குறிக்கும் ஒத்த சொற்கள்."
      },
      {
        "question": "'உதவித்தொகை' இச்சொல்லைப் பிரித்து எழுதக் கிடைப்பது எது?",
        "options": [
          "உதவி + தொகை",
          "உதவ + தொகை",
          "உதவிய + தொகை",
          "உதவு + தொகை"
        ],
        "answer": 0,
        "explanation": "பொருள்படப் பிரிக்கும் போது உதவி + தொகை எனப் பிரிக்க வேண்டும்."
      },
      {
        "question": "'யாருக்கு + எல்லாம்' இச்சொற்களைச் சேர்த்து எழுதக் கிடைப்பது எது?",
        "options": [
          "யாருக்குல்லாம்",
          "யாருக்கெல்லாம்",
          "யாருக்கு எலாம்",
          "யாருக்கல்லாம்"
        ],
        "answer": 1,
        "explanation": "யாருக்கு + எல்லாம் என்பது புணரும்போது 'யாருக்கெல்லாம்' என மாறும்."
      },
      {
        "question": "வாழ்க்கையில் முன்னேற உதவுவது எது?",
        "options": [
          "சோம்பல்",
          "கல்வி",
          "தீமை",
          "பொய்"
        ],
        "answer": 1,
        "explanation": "படிப்பறிவு என்னும் கல்வியே மனிதனை வாழ்க்கையில் முன்னேற்றப் பாதையில் கொண்டு செல்லும்."
      },
      {
        "question": "பொருத்துக: அ. பாதுகாப்பு தேடிச் செல்வோம் ஆ. கல்வி கற்கச் செல்வோம் இ. மருத்துவம் பார்க்கச் செல்வோம் - 1. மருத்துவமனை 2. பள்ளிக்கூடம் 3. காவல் நிலையம்",
        "options": [
          "அ-3, ஆ-2, இ-1",
          "அ-1, ஆ-2, இ-3",
          "அ-2, ஆ-3, இ-1",
          "அ-3, ஆ-1, இ-2"
        ],
        "answer": 0,
        "explanation": "பாதுகாப்பு-காவல் நிலையம், கல்வி-பள்ளிக்கூடம், மருத்துவம்-மருத்துவமனை என்பது சரியான இணை."
      },
      {
        "question": "பொருத்துக: அ. அஞ்சல்தலை வாங்க ஆ. பயணம் செய்ய - 1. பேருந்து நிலையம் 2. அஞ்சல் நிலையம்",
        "options": [
          "அ-2, ஆ-1",
          "அ-1, ஆ-2",
          "இரண்டும் தவறு",
          "விடை தெரியவில்லை"
        ],
        "answer": 0,
        "explanation": "அஞ்சல்தலை வாங்க அஞ்சல் நிலையத்திற்கும், பயணம் செய்யப் பேருந்து நிலையத்திற்கும் செல்வோம்."
      },
      {
        "question": "ஒப்புமை: கடிதம் : அஞ்சல்காரர் :: பாடம் கற்பிப்பவர் : ?",
        "options": [
          "மருத்துவர்",
          "காவலர்",
          "ஆசிரியர்",
          "தலைவர்"
        ],
        "answer": 2,
        "explanation": "கடிதம் கொடுப்பவர் அஞ்சல்காரர் என்பது போல, பாடம் கற்பிப்பவர் ஆசிரியர் ஆவார்."
      },
      {
        "question": "ஒப்புமை: உடல்நலம் : மருத்துவமனை :: பாதுகாப்பு : ?",
        "options": [
          "பேருந்து நிலையம்",
          "பள்ளிக்கூடம்",
          "அஞ்சல் நிலையம்",
          "காவல் நிலையம்"
        ],
        "answer": 3,
        "explanation": "உடல்நலம் பெற மருத்துவமனை செல்வது போல, பாதுகாப்பு தேடிக் காவல் நிலையம் செல்வோம்."
      },
      {
        "question": "கூற்று: பொன்வண்ணனுக்கு அரசின் சிறுதொழில் உதவித்தொகை கிடைத்தது. காரணம்: அவர் படித்தவர் என்பதால் அஞ்சலை உடனடியாகப் படித்தார்.",
        "options": [
          "கூற்றும் காரணமும் சரி",
          "கூற்று சரி, காரணம் தவறு",
          "கூற்று தவறு, காரணம் சரி",
          "கூற்றும் காரணமும் தவறு"
        ],
        "answer": 3,
        "explanation": "அவருக்குப் படிக்கத் தெரியாது, அதனால் அவர் கூட்டத்தில் பங்கேற்கவில்லை, உதவித்தொகையும் கிடைக்கவில்லை. எனவே இரண்டும் தவறு."
      },
      {
        "question": "கூற்று: பொன்வண்ணனின் மகனுக்குச் சரியாகப் படிக்கத் தெரியவில்லை. காரணம்: அவன் தந்தைக்கு உதவி செய்வதற்காக அடிக்கடி பள்ளிக்கு விடுப்பு எடுத்தான்.",
        "options": [
          "கூற்றும் காரணமும் சரி",
          "கூற்று சரி, காரணம் தவறு",
          "கூற்று தவறு, காரணம் சரி",
          "கூற்றும் காரணமும் தவறு"
        ],
        "answer": 0,
        "explanation": "மிதிவண்டிக் கடையில் வேலை செய்வதற்காக அடிக்கடி விடுப்பு எடுத்ததாலேயே அவனுக்குப் படிக்கத் தெரியாமல் போனது. எனவே இரண்டும் சரி."
      },
      {
        "question": "கூற்று: ஜூன் 12 குழந்தைத்தொழிலாளர் ஒழிப்பு நாளாகக் கடைப்பிடிக்கப்படுகிறது. காரணம்: குழந்தைகளை வேலைக்கு அமர்த்துவது சட்டப்படி குற்றமாகும் என்பதை வலியுறுத்த.",
        "options": [
          "கூற்றும் காரணமும் சரி",
          "கூற்று சரி, காரணம் தவறு",
          "கூற்று தவறு, காரணம் சரி",
          "கூற்றும் காரணமும் தவறு"
        ],
        "answer": 0,
        "explanation": "குழந்தைகளை வேலைக்கு அமர்த்துவது குற்றமாகும் எனச் சட்டம் கூறுகிறது, இதை வலியுறுத்தவே ஜூன் 12 கடைப்பிடிக்கப்படுகிறது."
      },
      {
        "question": "படிக்கத் தெரியாத காரணத்தால் பொன்வண்ணன் இழந்தது எதனை?",
        "options": [
          "மிதிவண்டி கடையை",
          "சிறுதொழில் தொடங்குவதற்கான அரசின் உதவித்தொகையை",
          "தன்னுடைய சொந்த வீட்டை",
          "ஊராட்சி மன்றத் தலைவர் பதவியை"
        ],
        "answer": 1,
        "explanation": "கடிதத்தைப் படிக்கத் தெரியாததால் கூட்டத்தில் பங்கேற்காமல் அரசின் உதவித்தொகையை இழந்தார்."
      },
      {
        "question": "அரசின் திட்டத்தின் மூலம் வழங்கப்படும் உதவித்தொகை எதற்காகப் பயன்படுத்தப்பட வேண்டும் எனத் தலைவர் கூறினார்?",
        "options": [
          "பள்ளி கட்டணம் செலுத்த",
          "சிறுதொழில் தொடங்க",
          "வாகனம் வாங்க",
          "மருத்துவச் செலவிற்கு"
        ],
        "answer": 1,
        "explanation": "சிறுதொழில் தொடங்குவதற்கான உதவித்தொகை வழங்கும் அரசின் திட்டம் என்று தலைவர் தெளிவாகக் கூறுகிறார்."
      },
      {
        "question": "பொன்வண்ணன் தன் மகனைக் கடையில் உதவிக்கு அழைத்தது சரியான செயலா?",
        "options": [
          "ஆம், தந்தைக்கும் மகனுக்கும் வருமானம் வரும்",
          "இல்லை, இது குழந்தையின் கல்வியைப் பாதிக்கும் மற்றும் சட்டப்படி குற்றம்",
          "ஆம், சிறு வயதிலேயே தொழில் கற்றுக்கொள்ளலாம்",
          "இல்லை, கடை வேலை மிகவும் கடினமானது என்பதால்"
        ],
        "answer": 1,
        "explanation": "குழந்தைகளைப் பள்ளிக்கு அனுப்பாமல் வேலைக்கு அனுப்புவது கல்வியைப் பறிக்கும் செயலாகும் மற்றும் இது சட்டப்படி குற்றமாகும்."
      },
      {
        "question": "'அஞ்சல்' என்பதன் இணையான ஆங்கிலச் சொல் என்ன?",
        "options": [
          "Telegram",
          "Post / Mail",
          "Message",
          "Call"
        ],
        "answer": 1,
        "explanation": "அஞ்சல் என்பது தபால் அல்லது Post என்பதைக் குறிக்கிறது."
      },
      {
        "question": "மிதிவண்டி என்பதைப் பேச்சுவழக்கில் நாம் எவ்வாறு அழைப்போம்?",
        "options": [
          "பைக்",
          "கார்",
          "சைக்கிள்",
          "ஸ்கூட்டர்"
        ],
        "answer": 2,
        "explanation": "மிதிவண்டி என்பது ஆங்கிலத்தில் Bicycle, பேச்சுவழக்கில் சைக்கிள் எனப்படும்."
      },
      {
        "question": "'பழுதுபார்த்தல்' என்ற சொல்லின் பொருள் என்ன?",
        "options": [
          "புதிதாக உருவாக்குதல்",
          "சீர்செய்தல் அல்லது குறையை நீக்குதல்",
          "முழுவதும் அழித்தல்",
          "விற்பனை செய்தல்"
        ],
        "answer": 1,
        "explanation": "பழுதுபார்த்தல் (Repair) என்பது கெட்டுப்போன ஒரு பொருளை மீண்டும் சீர்செய்வதாகும்."
      },
      {
        "question": "தன்னுடைய மகனும் தன்னைப்போலப் படிக்காதவன் ஆகிவிடக் கூடாது என எண்ணி வருந்தியவர் யார்?",
        "options": [
          "ஊராட்சி மன்றத் தலைவர்",
          "ஆசிரியர்",
          "பொன்வண்ணன்",
          "கிராம மக்கள்"
        ],
        "answer": 2,
        "explanation": "பொன்வண்ணன் தன் மகனைத் தான் படிக்கத் தெரியாதவனாக ஆக்கிவிட்டோமே என எண்ணி வருந்தினார்."
      },
      {
        "question": "பொன்வண்ணன் யாருக்கு நன்றி கூறிவிட்டு அங்கிருந்து சென்றார்?",
        "options": [
          "அஞ்சல்காரருக்கு",
          "ஊராட்சி மன்றத் தலைவருக்கு",
          "ஆசிரியருக்கு",
          "தன் மகனுக்கு"
        ],
        "answer": 1,
        "explanation": "தன் தவற்றை உணர்ந்த பொன்வண்ணன், ஊராட்சி மன்றத் தலைவருக்கு நன்றி கூறிவிட்டு நடக்கத் தொடங்கினார்."
      },
      {
        "question": "பொன்வண்ணனின் தொழில் என்னவாக இருந்தது?",
        "options": [
          "விவசாயம் செய்தல்",
          "மிதிவண்டி பழுதுபார்த்தல்",
          "அஞ்சல் பட்டுவாடா செய்தல்",
          "பள்ளி ஆசிரியர்"
        ],
        "answer": 1,
        "explanation": "அவர் மிதிவண்டி பழுதுபார்க்கும் கடை வைத்திருந்தார்."
      },
      {
        "question": "கல்வியின் முக்கியத்துவத்தை உணர்த்தும் பழமொழி கீழ்க்கண்டவற்றுள் எது?",
        "options": [
          "மின்னுவதெல்லாம் பொன்னல்ல",
          "கல்வி கண் போன்றது",
          "காற்றுள்ளபோதே தூற்றிக்கொள்",
          "ஆழம் தெரியாமல் காலை விடாதே"
        ],
        "answer": 1,
        "explanation": "கல்வியே ஒரு மனிதனுக்குக் கண் போன்று உலகத்தை அறிந்துகொள்ள உதவுகிறது என்பதை 'கல்வி கண் போன்றது' என்ற பழமொழி உணர்த்துகிறது."
      },
      {
        "question": "உங்களுக்குப் படிக்கத் தெரியாத மொழியில் ஒரு முக்கியக் கடிதம் வருகிறது, நீங்கள் என்ன செய்வீர்கள்?",
        "options": [
          "கடிதத்தைக் கிழித்துப் போட்டுவிடுவேன்",
          "படிக்கத் தெரிந்தவர்களிடம் கொடுத்துப் படித்துத் தெரிந்து கொள்வேன்",
          "கடிதத்தை அப்படியே அலமாரியில் வைத்துவிடுவேன்",
          "அஞ்சல்காரரிடமே திருப்பிக் கொடுத்துவிடுவேன்"
        ],
        "answer": 1,
        "explanation": "படிக்கத் தெரியாவிட்டால், படித்தவர்களின் உதவியை நாடி அதில் உள்ள செய்தியைத் தெரிந்துகொள்வதே விவேகமானது."
      },
      {
        "question": "உங்கள் பகுதியில் ஒரு சிறுவன் பள்ளிக்குச் செல்லாமல் செங்கல் சூளையில் வேலை செய்கிறான். நீங்கள் என்ன செய்வீர்கள்?",
        "options": [
          "அது அவர்களின் குடும்பப் பிரச்சனை எனக் கண்டுகொள்ள மாட்டேன்",
          "குழந்தைத் தொழிலாளர் ஒழிப்பு மையத்திற்கோ அல்லது அதிகாரிகளுக்கோ தகவல் அளிப்பேன்",
          "நானும் அவனுடன் சேர்ந்து வேலைக்குச் செல்வேன்",
          "அவனை வேலைக்குச் செல்லுமாறு ஊக்குவிப்பேன்"
        ],
        "answer": 1,
        "explanation": "குழந்தைத்தொழிலாளர் முறை சட்டப்படி குற்றம் என்பதால், உரிய அதிகாரிகளுக்குத் தகவல் அளித்துப் பள்ளிக்குச் செல்ல உதவுவதே சரியான குடிமகனின் கடமையாகும்."
      },
      {
        "question": "பொன்வண்ணன் தன் மகனைத் தொடர்ந்து கடைக்கு வேலைக்கு அனுப்பியிருந்தால் அவனது எதிர்காலம் எப்படி இருந்திருக்கும்?",
        "options": [
          "மிகப்பெரிய தொழிலதிபராக ஆகியிருப்பான்",
          "தந்தையைப்போலவே படிப்பறிவில்லாமல் வாழ்க்கையில் பல வாய்ப்புகளை இழந்து துன்பப்பட்டிருப்பான்",
          "அரசு அதிகாரியாக ஆகியிருப்பான்",
          "எவ்விதப் பாதிப்பும் இருந்திருக்காது"
        ],
        "answer": 1,
        "explanation": "கல்வி கற்காவிட்டால், கடிதம் படிக்கத் தெரியாமல் தந்தை வாய்ப்பை இழந்தது போல, அவனும் பிற்காலத்தில் பல இழப்புகளைச் சந்தித்திருப்பான்."
      },
      {
        "question": "'கல்வி கண் போன்றது' என்ற தலைப்பு இக்கதைக்கு எவ்வாறு பொருந்துகிறது?",
        "options": [
          "பொன்வண்ணனுக்குக் கண் பார்வை இல்லாததால்",
          "கண் இல்லாவிட்டால் உலகம் இருள், கல்வி இல்லாவிட்டால் மனிதனின் வாழ்க்கையே இருள் என்பதை உணர்த்துவதால்",
          "பள்ளிக்கூடம் கண்ணைப் போல வட்டமாக இருந்ததால்",
          "கல்வி கற்கக் கண்கள் மட்டும் போதும் என்பதால்"
        ],
        "answer": 1,
        "explanation": "படிப்பறிவு என்னும் 'கண்' இல்லாததால் பொன்வண்ணன் தனக்கு வந்த வாய்ப்பைக் காணாமல் இருளில் நின்றார். கல்வியே அகக்கண்."
      },
      {
        "question": "அரசு ஏன் சிறுதொழில் தொடங்குவதற்கான உதவித்தொகையை வழங்குகிறது?",
        "options": [
          "ஊராட்சி மன்றத் தலைவருக்குக் கொடுப்பதற்காக",
          "பொருளாதாரத்தில் பின்தங்கியவர்கள் தொழில் தொடங்கித் தங்கள் வாழ்வில் முன்னேறுவதற்காக",
          "பணத்தை வீணடிப்பதற்காக",
          "குழந்தைகளை வேலைக்கு அமர்த்துவதற்காக"
        ],
        "answer": 1,
        "explanation": "ஏழை எளிய மக்கள் சுயமாகத் தொழில் செய்து பொருளாதாரத்தில் முன்னேற வேண்டும் என்பதே அரசின் உதவித்தொகைத் திட்டங்களின் நோக்கமாகும்."
      },
      {
        "question": "பொன்வண்ணனின் தவற்றை அவரிடம் பலமுறை சுட்டிக்காட்டிய நபர் யார்?",
        "options": [
          "அஞ்சல்காரர்",
          "ஊராட்சி மன்றத் தலைவர்",
          "அவனுடைய ஆசிரியர்",
          "மனைவி"
        ],
        "answer": 2,
        "explanation": "மகன் பள்ளிக்கு விடுப்பு எடுப்பது குறித்து அவனுடைய ஆசிரியர் பலமுறை கூறியிருந்ததாகப் பொன்வண்ணன் நினைவுகூர்கிறார்."
      },
      {
        "question": "ஒரு பெற்றோர் தன் குழந்தைக்குச் செய்ய வேண்டிய மிகச் சிறந்த கடமை எதுவாக இருக்க முடியும் என இக்கதை உணர்த்துகிறது?",
        "options": [
          "நிறைய சொத்து சேர்த்து வைப்பது",
          "குழந்தைக்குச் சிறந்த கல்வியை வழங்குவது",
          "சிறுவயதிலேயே வேலைக்கு அனுப்புவது",
          "அதிக விலையுள்ள ஆடைகளை வாங்கிக் கொடுப்பது"
        ],
        "answer": 1,
        "explanation": "சொத்துகளைவிட ஒருவருக்கு அழியாத செல்வம் கல்வியே. அக்கல்வியைக் கொடுப்பதே பெற்றோரின் தலையாய கடமை."
      },
      {
        "question": "ஒப்புமை: இருள் : ஒளி :: அறியாமை : ?",
        "options": [
          "கல்வி",
          "பணம்",
          "பள்ளி",
          "ஆசிரியர்"
        ],
        "answer": 0,
        "explanation": "இருளை அகற்றுவது ஒளி, அதுபோல அறியாமையை அகற்றுவது கல்வி ஆகும்."
      },
      {
        "question": "கிராமசபைக் கூட்டம் பொதுவாக எங்கே நடைபெறும்?",
        "options": [
          "பள்ளிக்கூடத்தில்",
          "காவல் நிலையத்தில்",
          "ஊராட்சி மன்ற அலுவலகத்தில்",
          "மருத்துவமனையில்"
        ],
        "answer": 2,
        "explanation": "கதையின் தொடக்கத்திலேயே விரியூர் கிராமத்திலுள்ள ஊராட்சி மன்ற அலுவலகத்தில் கிராமசபைக் கூட்டம் நடைபெற்றதாகக் கூறப்பட்டுள்ளது."
      },
      {
        "question": "பொன்வண்ணன் தன்னுடைய மகன் நன்கு படித்து வாழ்வில் என்னவாக வேண்டும் என எண்ணினார்?",
        "options": [
          "வியாபாரியாக",
          "முன்னேற வேண்டும்",
          "கடை ஊழியராக",
          "அஞ்சல்காரராக"
        ],
        "answer": 1,
        "explanation": "என் மகனாவது நன்கு படித்து வாழ்வில் முன்னேறட்டும் எனப் பொன்வண்ணன் எண்ணினார்."
      },
      {
        "question": "ஒரு கடிதம் அல்லது அஞ்சல் ஒருவருக்கு வந்திருப்பதை எப்படி அறிந்துகொள்வது?",
        "options": [
          "காவல் நிலையம் மூலம்",
          "மருத்துவமனை மூலம்",
          "அஞ்சல்காரர் அதை உரியவரிடம் கொடுப்பதன் மூலம்",
          "பேருந்து ஓட்டுநர் மூலம்"
        ],
        "answer": 2,
        "explanation": "அஞ்சல் நிலையத்திலிருந்து அஞ்சல்காரர் (Postman) உரிய முகவரிக்குக் கடிதத்தைக் கொண்டு வந்து சேர்ப்பார்."
      },
      {
        "question": "அறிவுடைய ஒரு சமுதாயத்தை உருவாக்க நாம் எதை ஒழிக்க வேண்டும்?",
        "options": [
          "கல்வியை",
          "பள்ளிக்கூடத்தை",
          "குழந்தைத் தொழிலாளர் முறையை",
          "விவசாயத்தை"
        ],
        "answer": 2,
        "explanation": "குழந்தைத் தொழிலாளர் முறையை ஒழித்து, அனைத்துக் குழந்தைகளையும் பள்ளிக்கு அனுப்புவதன் மூலமே அறிவுடைய சமுதாயத்தை உருவாக்க முடியும்."
      },
      {
        "question": "பொன்வண்ணன் வாழ்க்கையில் ஏற்பட்ட இந்த நிகழ்வு அவருக்கு எதை உணர்த்தியது?",
        "options": [
          "பணத்தின் மதிப்பை",
          "மிதிவண்டியின் அருமையை",
          "கல்வியின் இன்றியமையாமையை",
          "அரசு அலுவலகங்களின் செயல்பாட்டை"
        ],
        "answer": 2,
        "explanation": "படிக்கத் தெரியாததால் வந்த இழப்பைக் கண்ட பொன்வண்ணன், கல்வியின் முக்கியத்துவத்தை (இன்றியமையாமையை) முழுமையாக உணர்ந்தார்."
      }
    ]
  },
  "material": {
    "sections": [
      {
        "title": "பாடச் சுருக்கம்: விரிவான கதைக்களம்",
        "content": "விரியூர் கிராமத்திலுள்ள ஊராட்சி மன்ற அலுவலகத்தில் நடைபெற்ற கிராமசபைக் கூட்டத்தில், சிறுதொழில் தொடங்குவதற்கான உதவித்தொகை வழங்கும் அரசின் திட்டம் குறித்து ஊராட்சி மன்றத் தலைவர் பேசினார். யாருக்கெல்லாம் உதவித்தொகை வந்துள்ளதோ அவர்களின் பெயர்களைப் படித்தார். பொன்வண்ணன் ஆவலோடு எதிர்பார்த்தும் அவர் பெயர் வரவில்லை. வறுமையில் வாடும் தனக்கு ஏன் உதவித்தொகை வரவில்லை என பொன்வண்ணன் தலைவரிடம் கேட்டார். அதற்குத் தலைவர், உதவி தேவைப்படுவோருக்கான கூட்டம் பற்றிய அஞ்சலை அனுப்பியிருந்ததாகக் கூறினார். கடந்த வாரமே அஞ்சல்காரர் கடிதம் கொடுத்தும், தனக்குப் படிக்கத் தெரியாததால் பொன்வண்ணன் அதனை அப்படியே வைத்துவிட்டதாகக் கூறினார்."
      },
      {
        "title": "பொன்வண்ணனின் குற்ற உணர்வும் மனமாற்றமும்",
        "content": "பொன்வண்ணனுக்குப் படிக்கத் தெரியாவிட்டாலும், பள்ளியில் படிக்கும் அவனது மகனாவது அந்தக் கடிதத்தைப் படித்துச் சொல்லியிருக்கலாமே எனத் தலைவர் கேட்டார். அதற்குப் பொன்வண்ணன், தான் வைத்திருக்கும் மிதிவண்டி பழுதுபார்க்கும் கடையில் உதவி செய்வதற்காகத் தன் மகனை அடிக்கடி பள்ளிக்கு விடுப்பு எடுக்கச் செய்ததையும், அதனால் அவனுக்குச் சரியாக எழுதவோ படிக்கவோ தெரியாமல் போனதையும் எண்ணிக் குற்ற உணர்வோடு தலைகுனிந்தார். ஆசிரியரும் இதைப்பற்றிக் கூறியிருந்ததை நினைத்து, தன் மகனைப் படிக்கத் தெரியாதவனாக ஆக்கிவிட்டோமே என வருந்தினார். இனிமேல் தன் மகனை வேலைக்காகப் பள்ளியை விட்டு நிறுத்த மாட்டேன், தினமும் பள்ளிக்கு அனுப்புவேன் என்று உறுதியெடுத்துக்கொண்டு, தலைவருக்கு நன்றி கூறிவிட்டு அங்கிருந்து நடந்தார்."
      },
      {
        "title": "அறிந்துகொள்வோம் (முக்கிய குறிப்பு)",
        "content": "குழந்தைகளை வேலைக்கு அமர்த்துவது சட்டப்படி குற்றமாகும். இதனை வலியுறுத்தும் விதமாகக் 'குழந்தைத்தொழிலாளர் ஒழிப்புநாள்' ஆண்டுதோறும் ஜூன் 12 அன்று கடைப்பிடிக்கப்படுகிறது."
      },
      {
        "title": "பின்புற மதிப்பீட்டு வினாக்கள் - சரியான விடையைத் தெரிவு செய்தல்",
        "content": "1. துன்பம் இச்சொல்லின் எதிர்ச்சொல் - இன்பம்.\n2. உதவித்தொகை இச்சொல்லைப் பிரித்து எழுதக் கிடைப்பது - உதவி + தொகை.\n3. யாருக்கு + எல்லாம் இச்சொற்களைச் சேர்த்து எழுதக் கிடைப்பது - யாருக்கெல்லாம்.\n4. வாழ்க்கையில் முன்னேற உதவுவது - கல்வி."
      },
      {
        "title": "பின்புற மதிப்பீட்டு வினாக்கள் - வினாக்களுக்கு விடையளிப்பேன்",
        "content": "1. ஊராட்சி மன்றத் தலைவர் கிராமசபைக் கூட்டத்தில் எதனைக் குறித்துப் பேசினார்? - சிறுதொழில் தொடங்குவதற்கான உதவித்தொகை வழங்கும் அரசின் திட்டம் குறித்துப் பேசினார்.\n2. பொன்வண்ணனுக்கு உதவித்தொகை ஏன் கிடைக்கவில்லை? - அவருக்குப் படிக்கத் தெரியாததால், அஞ்சல் மூலம் வந்த தகவலைப் படித்துக் கூட்டத்தில் கலந்து கொள்ளவில்லை. அதனால் அவருக்கு உதவித்தொகை கிடைக்கவில்லை."
      },
      {
        "title": "எதற்காக, எங்கே செல்வோம்? - இணைப்போம் (பொருத்துக)",
        "content": "1. பாதுகாப்பு தேடிச் செல்வோம் - காவல் நிலையம்\n2. கல்வி கற்கச் செல்வோம் - பள்ளிக்கூடம்\n3. மருத்துவம் பார்க்கச் செல்வோம் - மருத்துவமனை\n4. அஞ்சல்தலை வாங்கச் செல்வோம் - அஞ்சல் நிலையம்\n5. பயணம் செய்யச் செல்வோம் - பேருந்து நிலையம்"
      }
    ]
  }
}