{
  "lesson_meta": {
    "title": "அலகு 3: தாவரங்கள்",
    "unit": "3",
    "grade": "4",
    "term": "2",
    "subject": "science",
    "code": "sci_4_t2_l3",
    "status": "final"
  },
  "quiz": {
    "questions": [
      {
        "question": "இலையின் பரந்த மற்றும் தட்டையான பகுதி எவ்வாறு அழைக்கப்படுகிறது?",
        "options": [
          "இலை நுனி",
          "இலைத்தாள் (லாமினா)",
          "இலைக்காம்பு",
          "மைய நரம்பு"
        ],
        "answer": 1,
        "explanation": "இலையின் பரந்த தட்டையான பகுதி இலைத்தாள் அல்லது லாமினா என்று அழைக்கப்படுகிறது."
      },
      {
        "question": "நீர் மற்றும் தாதுக்களை இலையின் பல்வேறு பகுதிகளுக்கு கொண்டு செல்லும் வெற்றுக்குழாய்கள் எவை?",
        "options": [
          "நரம்புகள்",
          "இலைத்துளைகள்",
          "இலைக்காம்பு",
          "பச்சையம்"
        ],
        "answer": 0,
        "explanation": "மைய நரம்பிலிருந்து பிரியும் கிளை நரம்புகளே நீர் மற்றும் தாதுக்களைக் கொண்டு செல்லும் வெற்றுக்குழாய்கள் ஆகும்."
      },
      {
        "question": "இலையை முதன்மைத் தண்டுப் பகுதியுடன் இணைக்கும் பாகம் எது?",
        "options": [
          "இலைக்காம்பு",
          "இலை நுனி",
          "நரம்புகள்",
          "இலைத்தாள்"
        ],
        "answer": 0,
        "explanation": "இலைக்காம்பு (Petiole) என்பது இலையை தாவரத்தின் தண்டுடன் இணைக்கும் பகுதியாகும்."
      },
      {
        "question": "தாவரங்களின் சுவாசத்திற்கும், வாயுப்பரிமாற்றத்திற்கும் உதவும் இலையின் பாகம் எது?",
        "options": [
          "பச்சையம்",
          "மைய நரம்பு",
          "இலைத்துளைகள்",
          "இலை நுனி"
        ],
        "answer": 2,
        "explanation": "இலையின் அடிப்பகுதியில் காணப்படும் சிறிய துளைகளான இலைத்துளைகள் வழியாகவே காற்று உட்புறமும் வெளிப்புறமும் செல்கிறது."
      },
      {
        "question": "ஒளிச்சேர்க்கையின் போது தாவரங்கள் எடுத்துக்கொள்ளும் வாயு எது?",
        "options": [
          "நைட்ரஜன்",
          "ஆக்ஸிஜன்",
          "கார்பன் டைஆக்ஸைடு",
          "ஹைட்ரஜன்"
        ],
        "answer": 2,
        "explanation": "தாவரங்கள் உணவு தயாரிக்க காற்றில் உள்ள கார்பன் டைஆக்ஸைடை இலைத்துளைகள் வழியே உறிஞ்சுகின்றன."
      },
      {
        "question": "தாவரங்கள் தங்கள் உணவை தாங்களே தயாரிக்கும் செயல்முறையின் பெயர் என்ன?",
        "options": [
          "நீராவிப்போக்கு",
          "சுவாசித்தல்",
          "ஒளிச்சேர்க்கை",
          "மகரந்தச்சேர்க்கை"
        ],
        "answer": 2,
        "explanation": "சூரிய ஒளியின் முன்னிலையில் தாவரங்கள் உணவு தயாரிக்கும் நிகழ்வு ஒளிச்சேர்க்கை எனப்படும்."
      },
      {
        "question": "ஒளிச்சேர்க்கைக்குத் தேவையான மூலப்பொருட்களில் பொருந்தாதது எது?",
        "options": [
          "சூரிய ஒளி",
          "நீர்",
          "ஆக்ஸிஜன்",
          "கார்பன் டைஆக்ஸைடு"
        ],
        "answer": 2,
        "explanation": "ஒளிச்சேர்க்கைக்கு கார்பன் டைஆக்ஸைடு, நீர், சூரிய ஒளி மற்றும் பச்சையம் தேவை. ஆக்ஸிஜன் என்பது இதன் மூலம் வெளியேற்றப்படும் வாயுவாகும்."
      },
      {
        "question": "பெரும்பாலான இலைகள் பச்சை நிறத்தில் காணப்படக் காரணமான நிறமி எது?",
        "options": [
          "குளோரோபில் (பச்சையம்)",
          "மெலனின்",
          "கரோட்டின்",
          "சாந்தோபில்"
        ],
        "answer": 0,
        "explanation": "இலைகளில் உள்ள குளோரோபில் எனப்படும் பச்சை நிறமியே சூரிய ஒளியை ஈர்க்க உதவுகிறது, மேலும் இலைகளுக்கு பச்சை நிறத்தைத் தருகிறது."
      },
      {
        "question": "தங்களுக்கான உணவை தாங்களே தயாரித்துக் கொள்வதால் தாவரங்கள் எவ்வாறு அழைக்கப்படுகின்றன?",
        "options": [
          "இரண்டாம் நிலை நுகர்வோர்கள்",
          "முதன்மை உற்பத்தியாளர்கள்",
          "சிதைப்பவைகள்",
          "முதல் நிலை நுகர்வோர்கள்"
        ],
        "answer": 1,
        "explanation": "தாவரங்கள் தங்களுக்கும் பிற உயிரினங்களுக்கும் தேவையான உணவை தாமே தயாரிப்பதால் முதன்மை உற்பத்தியாளர்கள் எனப்படுகின்றன."
      },
      {
        "question": "சரியா தவறா: கள்ளிச்செடி போன்ற தாவரங்களில் இலைகள் இல்லாததால் அவை ஒளிச்சேர்க்கை செய்வதில்லை.",
        "options": [
          "சரி",
          "தவறு",
          "சில நேரங்களில் சரி",
          "கூற இயலாது"
        ],
        "answer": 1,
        "explanation": "தவறு. கள்ளிச்செடிகளுக்கு இலைகள் இல்லை என்றாலும், அவை தமது பச்சையான தண்டுகள் மூலமாக உணவைத் தயாரித்துக் கொள்கின்றன."
      },
      {
        "question": "பின்வருவனவற்றில் பூக்கும் தாவரத்திற்கு எடுத்துக்காட்டு எது?",
        "options": [
          "பாசிகள்",
          "பெரணி",
          "வேம்பு",
          "பூஞ்சைகள்"
        ],
        "answer": 2,
        "explanation": "வேம்பு, மா, வேர்க்கடலை, நெல் ஆகியவை பூக்கும் தாவரங்கள் ஆகும். மற்றவை பூவாத் தாவரங்கள்."
      },
      {
        "question": "பூக்கும் தாவரங்கள் எதன் மூலம் தங்களது இனப்பெருக்கத்தை மேற்கொள்கின்றன?",
        "options": [
          "வேர்கள்",
          "விளைபொருட்கள்",
          "ஸ்போர்கள்",
          "பாலின செல்களால் விதைகளை உருவாக்கி"
        ],
        "answer": 3,
        "explanation": "பூக்கும் தாவரங்கள் மலர்களைக் கொண்டு, பாலின செல்களால் விதைகளை உருவாக்கி இனப்பெருக்கம் செய்கின்றன."
      },
      {
        "question": "பூவாத் தாவரங்கள் இனப்பெருக்கம் செய்யும் முறை என்ன?",
        "options": [
          "விதைகள் மூலம்",
          "ஸ்போர்கள் மூலம்",
          "கனிகள் மூலம்",
          "மகரந்தத்தூள் மூலம்"
        ],
        "answer": 1,
        "explanation": "பூவாத் தாவரங்கள் விதைகளை உற்பத்தி செய்வதில்லை. அவை ஸ்போர்கள் (Spores) மூலமாகவே இனப்பெருக்கம் செய்கின்றன."
      },
      {
        "question": "பின்வருவனவற்றில் பூவாத் தாவரம் எது?",
        "options": [
          "நெல்",
          "பெரணி",
          "மா",
          "வேர்க்கடலை"
        ],
        "answer": 1,
        "explanation": "பாசிகள், பூஞ்சைகள், பெரணி போன்றவை மலர்கள் இன்றி இனப்பெருக்கம் செய்யும் பூவாத் தாவரங்கள் ஆகும்."
      },
      {
        "question": "பச்சையம் உள்ள தாவரங்கள் எவ்வாறு அழைக்கப்படுகின்றன?",
        "options": [
          "ஹெட்டிரோட்ரோப்கள்",
          "ஆட்டோட்ரோப்கள் (தற்சார்பு உயிரினங்கள்)",
          "சாறுண்ணிகள்",
          "ஒட்டுண்ணிகள்"
        ],
        "answer": 1,
        "explanation": "பச்சையம் உள்ள தாவரங்கள் தமக்குத் தேவையான உணவை தாமே தயாரிப்பதால் ஆட்டோட்ரோப்கள் (தற்சார்பு உயிரினங்கள்) எனப்படுகின்றன."
      },
      {
        "question": "ஒப்புமை தருக: பச்சையம் உள்ளவை : நெல் :: பச்சையம் அற்றவை : ?",
        "options": [
          "புல்",
          "காளான்",
          "பாசிகள்",
          "மாமரம்"
        ],
        "answer": 1,
        "explanation": "புல், நெல், பாசிகள் போன்றவை பச்சையம் உள்ளவை. காளான், ரொட்டிக் காளான் போன்றவை பச்சையம் அற்ற பிறசார்பு தாவரங்கள் ஆகும்."
      },
      {
        "question": "பிறசார்பு உயிரினங்கள் (ஹெட்டிரோட்ரோப்கள்) என்று அழைக்கப்படுபவை எவை?",
        "options": [
          "பூக்கும் தாவரங்கள்",
          "பச்சையம் உள்ள தாவரங்கள்",
          "பச்சையம் அற்ற தாவரங்கள்",
          "விதையுள்ள தாவரங்கள்"
        ],
        "answer": 2,
        "explanation": "பச்சையம் இல்லாததால் தாமே உணவு தயாரிக்க முடியாமல் மற்ற உயிரினங்களை சார்ந்து வாழும் தாவரங்கள் பிறசார்பு உயிரினங்கள் எனப்படும்."
      },
      {
        "question": "மலர் மொட்டாக இருக்கும்போது அதனைப் பாதுகாக்கும் வெளிப்புற அடுக்கு எது?",
        "options": [
          "சூலகம்",
          "அல்லிவட்டம்",
          "புல்லிவட்டம்",
          "மகரந்தத்தாள் வட்டம்"
        ],
        "answer": 2,
        "explanation": "புல்லிவட்டம் என்பது மலரின் கீழ்ப்பகுதியில் பொதுவாக பச்சை நிறத்தில் காணப்படும், மொட்டினைப் பாதுகாக்கும் அடுக்கு ஆகும்."
      },
      {
        "question": "பூச்சிகளை ஈர்ப்பதற்காக பிரகாசமான நிறமுடைய மலரின் பாகம் எது?",
        "options": [
          "புல்லிவட்டம்",
          "அல்லிவட்டம்",
          "மகரந்தத்தாள்",
          "சூலகம்"
        ],
        "answer": 1,
        "explanation": "அல்லிவட்டம் (Petal) வண்ணமயமாகவும் வாசனையாகவும் இருந்து தேனீக்கள் மற்றும் வண்ணத்துப்பூச்சிகளை ஈர்த்து மகரந்தச்சேர்க்கைக்கு உதவுகிறது."
      },
      {
        "question": "மலரின் ஆண் பாகம் எவ்வாறு அழைக்கப்படுகிறது?",
        "options": [
          "புல்லிவட்டம்",
          "சூலகம்",
          "அல்லிவட்டம்",
          "மகரந்தத்தாள் வட்டம்"
        ],
        "answer": 3,
        "explanation": "மலரின் மையத்தில் உள்ள மகரந்தத்தாள் வட்டம் இனப்பெருக்கத்திற்கு உதவும் மகரந்தத் துகள்களைக் கொண்ட ஆண் பாகமாகும்."
      },
      {
        "question": "மகரந்தத் துகள்களுடன் இணைந்து கனியாக மாறும் மலரின் பெண் பாகம் எது?",
        "options": [
          "சூலகம்",
          "புல்லிவட்டம்",
          "அல்லிவட்டம்",
          "மகரந்தத்தாள்"
        ],
        "answer": 0,
        "explanation": "சூலகம் (Pistil) மலரின் நடுப்பகுதியில் காணப்படும் பெண் பாகமாகும். இதுவே பின்னாளில் கனியாக மாறுகிறது."
      },
      {
        "question": "உலகின் மிகப் பெரிய மலரான ரஃப்ளேசியா எந்த காடுகளில் காணப்படுகிறது?",
        "options": [
          "அமேசான் காடுகள்",
          "ஆப்பிரிக்க காடுகள்",
          "இந்தோனேசியாவின் மழைக்காடுகள்",
          "இந்தியாவின் மேற்குத் தொடர்ச்சி மலை"
        ],
        "answer": 2,
        "explanation": "உலகின் மிகப்பெரிய மலரான ரஃப்ளேசியா இந்தோனேசியாவின் மழைக்காடுகளில் காணப்படும் ஒரு அரிய வகை மலராகும்."
      },
      {
        "question": "குளிர்காலத்தில் பூக்கும் மலருக்கு எடுத்துக்காட்டு எது?",
        "options": [
          "சூரியகாந்தி",
          "டிசம்பர் பூ",
          "டாலியா",
          "மணிப்பூ (டியூலிப்)"
        ],
        "answer": 1,
        "explanation": "டிசம்பர் பூ, குளிர்கால மல்லிகை, சம்பங்கி ஆகியவை குளிர்காலத்தில் பூக்கும் பருவகால மலர்கள் ஆகும்."
      },
      {
        "question": "கோடைக்காலத்தில் பூக்கும் மலர்களைத் தேர்ந்தெடுக்கவும்.",
        "options": [
          "டாலியா, குங்குமப்பூ",
          "டிசம்பர் பூ, சம்பங்கி",
          "மல்லிகை, சூரியகாந்தி, ரோஜா",
          "மணிப்பூ, குறிஞ்சிப்பூ"
        ],
        "answer": 2,
        "explanation": "மல்லிகை, சூரியகாந்தி மற்றும் ரோஜா ஆகியவை பொதுவாக கோடைக்காலத்தில் பூக்கும் மலர்கள் ஆகும்."
      },
      {
        "question": "வசந்த காலத்தில் பூக்கக்கூடிய மலர் எது?",
        "options": [
          "டிசம்பர் பூ",
          "மணிப்பூ (டியூலிப்)",
          "சூரியகாந்தி",
          "சம்பங்கி"
        ],
        "answer": 1,
        "explanation": "மணிப்பூ (Tulip) என்பது வசந்த காலத்தில் (Spring season) பூக்கும் ஒரு மலராகும்."
      },
      {
        "question": "பன்னிரண்டு ஆண்டுகளுக்கு ஒருமுறை மட்டுமே பூக்கும் மலர் எது?",
        "options": [
          "கனகாம்பரம்",
          "ரஃப்ளேசியா",
          "குறிஞ்சிப் பூ",
          "சம்பங்கி"
        ],
        "answer": 2,
        "explanation": "குறிஞ்சிப் பூ என்பது 12 ஆண்டுகளுக்கு ஒருமுறை மட்டுமே மலைப்பகுதிகளில் மலரும் ஒரு சிறப்பு வாய்ந்த மலராகும்."
      },
      {
        "question": "அனைத்துப் பருவங்களிலும் மலரும் தன்மையுடைய மலர் எது?",
        "options": [
          "கனகாம்பரம்",
          "டாலியா",
          "குங்குமப்பூ",
          "ரோஜா"
        ],
        "answer": 0,
        "explanation": "கனகாம்பரம் குறிப்பிட்ட பருவம் என்றில்லாமல் அனைத்துப் பருவ காலங்களிலும் மலரக்கூடியது."
      },
      {
        "question": "மனிதர்களால் தற்செயலாகவோ அல்லது அழகுக்காகவோ ஓரிடத்திலிருந்து மற்றோர் இடத்திற்கு கொண்டுவரப்பட்ட தாவரங்கள் எவ்வாறு அழைக்கப்படுகின்றன?",
        "options": [
          "உள்ளூர் தாவரங்கள்",
          "அயல் தாவரங்கள்",
          "பழங்குடி தாவரங்கள்",
          "நீர்வாழ் தாவரங்கள்"
        ],
        "answer": 1,
        "explanation": "இயல்பாக வளரும் இடத்திலிருந்து கொண்டுவரப்பட்டு வளர்க்கப்படும் தாவரங்கள் அயல் தாவரங்கள் அல்லது அழகு தாவரங்கள் எனப்படும்."
      },
      {
        "question": "அயல் தாவரங்களுக்கு (அழகு தாவரங்கள்) எடுத்துக்காட்டு அல்லாதது எது?",
        "options": [
          "சைக்கஸ் (சாகோ பனை)",
          "விசிறி வாழை",
          "வேப்பமரம்",
          "குரோட்டன்ஸ்"
        ],
        "answer": 2,
        "explanation": "சைக்கஸ், பெரணி, குரோட்டன்ஸ், விசிறி வாழை, படகு அல்லி போன்றவை அயல்/அழகு தாவரங்கள். வேப்பமரம் நமது உள்ளூர் மரம்."
      },
      {
        "question": "வேளாண்மையை பாதிக்கும் மற்றும் அதன் மகரந்தத்துகள்கள் ஒவ்வாமையை (Allergy) ஏற்படுத்தும் களைச்செடி எது?",
        "options": [
          "பார்த்தீனியம்",
          "கற்றாழை",
          "பெரணி",
          "படகு அல்லி"
        ],
        "answer": 0,
        "explanation": "பார்த்தீனியம் என்பது திடீரென பரவி விளைச்சலை பாதிக்கும் மற்றும் தொட்டால் ஒவ்வாமை ஏற்படுத்தும் ஒரு களைச்செடியாகும்."
      },
      {
        "question": "கூற்று: பார்த்தீனியம் செடியை தொடுவதைத் தவிர்க்க வேண்டும். காரணம்: இத்தாவரத்தின் மகரந்தத் துகள்கள் இயற்கையிலேயே ஒவ்வாமை கொண்டவை.",
        "options": [
          "கூற்று சரி, காரணம் தவறு",
          "கூற்று தவறு, காரணம் சரி",
          "கூற்று, காரணம் இரண்டும் சரி. சரியான விளக்கம்.",
          "கூற்று, காரணம் இரண்டும் சரி. சரியான விளக்கமல்ல."
        ],
        "answer": 2,
        "explanation": "பார்த்தீனியம் மகரந்தங்கள் ஆஸ்துமா, தோல் வியாதி போன்ற ஒவ்வாமையை ஏற்படுத்துவதால் அதைத் தொடக்கூடாது என அறிவுறுத்தப்படுகிறது."
      },
      {
        "question": "வேர் பகுதியை உணவாகப் பயன்படுத்தும் தாவரம் எது?",
        "options": [
          "வெங்காயம்",
          "கேரட்",
          "கரும்பு",
          "உருளைக்கிழங்கு"
        ],
        "answer": 1,
        "explanation": "கேரட், பீட்ரூட், மரவள்ளிக்கிழங்கு ஆகியவை தாவரங்கள் உணவை வேர்களில் சேமித்து வைப்பதால் பருத்து காணப்படுகின்றன, அவை வேர் உணவாகும்."
      },
      {
        "question": "உருளைக்கிழங்கு என்பது தாவரத்தின் எந்த பாகமாகும்?",
        "options": [
          "வேர்",
          "இலை",
          "கனி",
          "தண்டு"
        ],
        "answer": 3,
        "explanation": "உருளைக்கிழங்கு, வெங்காயம், இஞ்சி, மஞ்சள் ஆகியவை நிலத்திற்கு அடியில் காணப்படும் மாற்றுரு அடைந்த தண்டுப்பகுதியாகும்."
      },
      {
        "question": "தண்டுப் பகுதியை உணவாக உட்கொள்ளும் தாவரங்களுக்கு சரியான எடுத்துக்காட்டுகளைக் காண்க.",
        "options": [
          "முட்டைக்கோஸ், முருங்கை",
          "கேரட், பீட்ரூட்",
          "வெங்காயம், மஞ்சள், கரும்பு",
          "வாழைப்பூ, காலிபிளவர்"
        ],
        "answer": 2,
        "explanation": "வெங்காயம், மஞ்சள், கரும்பு, இஞ்சி போன்றவை அதிகப்படியான உணவை தண்டுகளில் சேமிக்கின்றன."
      },
      {
        "question": "நாம் உணவாக உட்கொள்ளும் முட்டைக்கோஸ் தாவரத்தின் எப்பாகம்?",
        "options": [
          "தண்டு",
          "மலர்",
          "வேர்",
          "இலை"
        ],
        "answer": 3,
        "explanation": "முட்டைக்கோஸ், கொத்தமல்லி, முருங்கைக்கீரை போன்றவை உணவை இலைகளில் சேமிக்கின்றன. அவற்றை நாம் உணவாகப் பயன்படுத்துகிறோம்."
      },
      {
        "question": "உணவாகப் பயன்படும் பூக்களுக்கு எடுத்துக்காட்டு தருக.",
        "options": [
          "வாழைப்பூ, காலிபிளவர், கிராம்பு",
          "வெங்காயம், பூண்டு",
          "மா, பலா",
          "கேரட், பீட்ரூட்"
        ],
        "answer": 0,
        "explanation": "வாழைப்பூ, காலிபிளவர் மற்றும் நறுமணப்பொருளான கிராம்பு (இலவங்கம்) ஆகியவை உணவாக பயன்படும் மலர் பகுதிகளாகும்."
      },
      {
        "question": "விதைகளை (தானியங்கள்/பருப்புகள்) உணவாக உட்கொள்ளும் தாவரங்களுக்கு எடுத்துக்காட்டு எது?",
        "options": [
          "முருங்கை, கொத்தமல்லி",
          "அரிசி, வெந்தயம்",
          "வாழை, பலா",
          "கரும்பு, மஞ்சள்"
        ],
        "answer": 1,
        "explanation": "அரிசி, வெந்தயம், பருப்பு வகைகள், பயறு வகைகள் ஆகியவை நாம் உணவாக உட்கொள்ளும் விதைகளாகும்."
      },
      {
        "question": "விதைகளில் எந்த வகையான சத்துகள் அதிக அளவில் காணப்படுகின்றன?",
        "options": [
          "வைட்டமின்கள் மற்றும் தாதுக்கள்",
          "நீர்ச்சத்து மற்றும் கொழுப்பு",
          "கார்போஹைட்ரேட் மற்றும் புரதங்கள்",
          "நார்ச்சத்து மற்றும் இரும்புச்சத்து"
        ],
        "answer": 2,
        "explanation": "பருப்பு மற்றும் தானிய வகைகளான விதைகளில் கார்போஹைட்ரேட் மற்றும் புரதச்சத்துகள் அதிகம் நிறைந்துள்ளன."
      },
      {
        "question": "பூமியில் அதிக நாள் வாழும் உயிரினம் எது?",
        "options": [
          "யானை",
          "திமிங்கலம்",
          "கடலாமை",
          "மரங்கள்"
        ],
        "answer": 3,
        "explanation": "பூமியில் விலங்குகளை விட தாவரங்களே (குறிப்பாக மரங்கள்) பல்லாயிரம் ஆண்டுகள் வரை மிக அதிக காலம் வாழும் உயிரினங்கள் ஆகும்."
      },
      {
        "question": "ஒரு நாளில் 90 சென்டிமீட்டர் அளவு வரை மிக வேகமாக வளரக்கூடிய தாவரம் எது?",
        "options": [
          "கரும்பு",
          "மூங்கில்",
          "வாழை",
          "யூக்கலிப்டஸ்"
        ],
        "answer": 1,
        "explanation": "மூங்கில் மரங்கள் உலகில் மிக வேகமாக வளரக்கூடிய தாவரங்களில் ஒன்றாகும், இவை நாள் ஒன்றுக்கு 90 செ.மீ வரை வளரும்."
      },
      {
        "question": "பொருத்துக: \n1. பீட்ரூட் - அ. இலை \n2. இஞ்சி - ஆ. பூ \n3. கொத்தமல்லி - இ. வேர் \n4. காலிபிளவர் - ஈ. தண்டு",
        "options": [
          "1-இ, 2-ஈ, 3-அ, 4-ஆ",
          "1-அ, 2-ஆ, 3-இ, 4-ஈ",
          "1-ஈ, 2-இ, 3-ஆ, 4-அ",
          "1-இ, 2-அ, 3-ஈ, 4-ஆ"
        ],
        "answer": 0,
        "explanation": "பீட்ரூட் வேர்ப்பகுதி, இஞ்சி தண்டுப்பகுதி, கொத்தமல்லி இலைப்பகுதி, காலிபிளவர் பூப்பகுதி ஆகும்."
      },
      {
        "question": "வாழ்க்கைச் சூழல் வினா: உங்கள் தோட்டத்தில் உள்ள ஒரு செடியின் இலைகள் மஞ்சள் நிறமாக மாறுகின்றன. செடி உணவு தயாரிப்பதை நிறுத்தினால், செடியில் எந்த நிறமி குறைபாடாக இருக்கும்?",
        "options": [
          "கரோட்டின்",
          "மெலனின்",
          "குளோரோபில் (பச்சையம்)",
          "சாந்தோபில்"
        ],
        "answer": 2,
        "explanation": "தாவரம் உணவு தயாரிக்கவும், பச்சை நிறமாக இருக்கவும் குளோரோபில் எனப்படும் பச்சையம் மிக அவசியம்."
      },
      {
        "question": "வாழ்க்கைச் சூழல் வினா: ஒரு செடியை இருட்டான பெட்டிக்குள் வைத்து, தண்ணீர் மட்டும் ஊற்றி வந்தால் ஒரு வாரம் கழித்து அந்த செடி என்னவாகும்?",
        "options": [
          "வழக்கம் போல் வளரும்",
          "பச்சையாகவே இருக்கும்",
          "பூக்கள் பூக்கும்",
          "வாடிவிடும் மற்றும் நிறம் மாறும்"
        ],
        "answer": 3,
        "explanation": "ஒளிச்சேர்க்கைக்கு சூரிய ஒளி அவசியம். ஒளியில்லாததால் செடியால் உணவு தயாரிக்க முடியாது, எனவே அது வாடிவிடும்."
      },
      {
        "question": "தாவரங்களில் எந்தப் பகுதி தமக்குத் தேவையான உணவைத் தாமே தயாரிக்கும் தொழிற்சாலையாகச் செயல்படுகிறது?",
        "options": [
          "வேர்",
          "தண்டு",
          "கனி",
          "இலை"
        ],
        "answer": 3,
        "explanation": "இலைகளில் உள்ள பச்சையம் மூலம் ஒளிச்சேர்க்கை நடைபெறுவதால், இலைகள் தாவரத்தின் உணவுத் தொழிற்சாலைகள் எனப்படுகின்றன."
      },
      {
        "question": "கூற்று: காளான் தனக்குத் தேவையான உணவை தானே தயாரித்துக்கொள்கிறது. காரணம்: காளான் ஒரு பச்சையம் உள்ள தாவரமாகும்.",
        "options": [
          "கூற்று மற்றும் காரணம் இரண்டும் சரி",
          "கூற்று சரி, காரணம் தவறு",
          "கூற்று மற்றும் காரணம் இரண்டும் தவறு",
          "கூற்று தவறு, காரணம் சரி"
        ],
        "answer": 2,
        "explanation": "காளான் பச்சையம் இல்லாத தாவரம், எனவே அது தன் உணவை தானே தயாரிக்க முடியாது (பிறசார்பு உயிரி). இரண்டுமே தவறு."
      },
      {
        "question": "பாசிகள் எந்த வகை தாவரங்களுக்கு எடுத்துக்காட்டாகும்?",
        "options": [
          "பூக்கும் தாவரங்கள்",
          "பச்சையம் அற்ற தாவரங்கள்",
          "பூவாத் தாவரங்கள்",
          "விதையுள்ள தாவரங்கள்"
        ],
        "answer": 2,
        "explanation": "பாசிகள் மலர்களை உருவாக்குவதில்லை, ஸ்போர்கள் மூலம் இனப்பெருக்கம் செய்யும் பூவாத் தாவரங்களாகும். மேலும் இவற்றில் பச்சையம் உள்ளது."
      },
      {
        "question": "பூவாத் தாவரங்களில் எந்த வகை தாவரம் பச்சையம் இல்லாததால் பிறசார்பு உயிரினமாக செயல்படுகிறது?",
        "options": [
          "பெரணி",
          "காளான் மற்றும் பூஞ்சைகள்",
          "பாசிகள்",
          "விசிறி வாழை"
        ],
        "answer": 1,
        "explanation": "காளான், ரொட்டிக் காளான் போன்ற பூஞ்சைகள் பூவாத் தாவரங்கள் மட்டுமல்லாது, பச்சையம் அற்ற பிறசார்பு உயிரினங்களும் ஆகும்."
      },
      {
        "question": "மகரந்தச் சேர்க்கை நடைபெற மிக முக்கியமாகத் தேவைப்படும் மலரின் கவர்ச்சியான பாகம் எது?",
        "options": [
          "புல்லிவட்டம்",
          "சூலகம்",
          "மகரந்தத்தாள்",
          "அல்லிவட்டம்"
        ],
        "answer": 3,
        "explanation": "அல்லிவட்டம் பல வண்ணங்களில் இருப்பதால் பூச்சிகளை எளிதில் ஈர்த்து மகரந்தச்சேர்க்கை நடைபெற உதவுகிறது."
      },
      {
        "question": "கீழ்க்கண்டவற்றுள் எது இலையின் பாகம் அல்ல?",
        "options": [
          "மைய நரம்பு",
          "இலைக்காம்பு",
          "சூலகம்",
          "இலை நுனி"
        ],
        "answer": 2,
        "explanation": "சூலகம் என்பது மலரின் பெண்பாகமாகும். மற்றவை இலையின் பாகங்கள்."
      },
      {
        "question": "ஒளிச்சேர்க்கையின் போது தாவரங்கள் எடுத்துக்கொள்ளும் மற்றும் வெளியிடும் வாயுக்கள் முறையே:",
        "options": [
          "ஆக்ஸிஜன், நைட்ரஜன்",
          "கார்பன் டைஆக்ஸைடு, ஆக்ஸிஜன்",
          "ஆக்ஸிஜன், கார்பன் டைஆக்ஸைடு",
          "கார்பன் டைஆக்ஸைடு, ஹைட்ரஜன்"
        ],
        "answer": 1,
        "explanation": "தாவரங்கள் கார்பன் டைஆக்ஸைடை எடுத்துக்கொண்டு, ஆக்சிஜனை (உயிர்வளி) வெளியிடுகின்றன."
      },
      {
        "question": "பொருந்தாத ஒன்றைக் கண்டுபிடி: ரோஜா, படகு அல்லி, குரோட்டன்ஸ்.",
        "options": [
          "படகு அல்லி",
          "குரோட்டன்ஸ்",
          "ரோஜா",
          "அனைத்தும் பொருந்தும்"
        ],
        "answer": 2,
        "explanation": "படகு அல்லி, குரோட்டன்ஸ் ஆகியவை இலைகளுக்காக வளர்க்கப்படும் அலங்கார/அயல் தாவரங்கள். ரோஜா கோடைகால மலர் தாவரம்."
      },
      {
        "question": "பொருந்தாத ஒன்றைக் கண்டுபிடி: குங்குமப்பூ, டாலியா, ரோஜா.",
        "options": [
          "டாலியா",
          "குங்குமப்பூ",
          "ரோஜா",
          "எதுவுமில்லை"
        ],
        "answer": 2,
        "explanation": "குங்குமப்பூ மற்றும் டாலியா ஆகியவை இலையுதிர் காலத்தில் பூக்கும் மலர்கள். ரோஜா கோடைகாலத்தில் பூக்கும் மலர்."
      },
      {
        "question": "பொருந்தாத ஒன்றைக் கண்டுபிடி: டிசம்பர் பூ, சம்பங்கி பூ, மணிப்பூ (டியூலிப்).",
        "options": [
          "சம்பங்கி பூ",
          "டிசம்பர் பூ",
          "மணிப்பூ (டியூலிப்)",
          "அனைத்தும் குளிர்கால மலர்கள்"
        ],
        "answer": 2,
        "explanation": "டிசம்பர் பூ மற்றும் சம்பங்கி ஆகியவை குளிர்கால மலர்கள். மணிப்பூ (டியூலிப்) வசந்த காலத்தில் பூக்கும் மலராகும்."
      },
      {
        "question": "தாவரங்களில் வேர்கள் மூலம் உறிஞ்சப்படும் நீர் எந்தப் பாகத்தின் வழியாக இலைகளுக்குச் செல்கிறது?",
        "options": [
          "பூக்கள்",
          "கனிகள்",
          "இலைத்துளைகள்",
          "தண்டு மற்றும் கிளை நரம்புகள்"
        ],
        "answer": 3,
        "explanation": "வேர் உறிஞ்சும் நீரானது தண்டுப்பகுதி வழியாகச் சென்று, இலையில் உள்ள மைய நரம்பு மற்றும் கிளை நரம்புகள் மூலம் இலையை அடைகிறது."
      },
      {
        "question": "தாவரங்கள் இல்லாமல் மற்ற உயிரினங்களால் வாழ முடியாது, ஏனெனில்:",
        "options": [
          "தாவரங்கள் மட்டுமே முதன்மை உற்பத்தியாளர்கள்",
          "அவை ஆக்ஸிஜனை வெளியிடுகின்றன",
          "அவை உணவளிக்கின்றன",
          "மேற்கூறிய அனைத்தும் சரி"
        ],
        "answer": 3,
        "explanation": "தாவரங்கள் உணவைத் தயாரிப்பதுடன், விலங்குகள் சுவாசிக்கத் தேவையான ஆக்ஸிஜனையும் வெளியிடுவதால் அவை இன்றி பிற உயிரினங்கள் வாழ இயலாது."
      },
      {
        "question": "பிற உயிரினங்களை சார்ந்து வாழும் தாவரங்கள் (ஹெட்டிரோட்ரோப்கள்) எவற்றைக் கொண்டிருப்பதில்லை?",
        "options": [
          "வேர்",
          "பச்சையம்",
          "தண்டு",
          "துளைகள்"
        ],
        "answer": 1,
        "explanation": "பச்சையம் இல்லாததாலேயே அவற்றால் உணவு தயாரிக்க முடிவதில்லை, எனவே பிற உயிர்களை சார்ந்து வாழ்கின்றன."
      },
      {
        "question": "விதை மூலம் இனப்பெருக்கம் செய்யாத தாவரம் எது?",
        "options": [
          "மா",
          "நெல்",
          "ரொட்டிக் காளான்",
          "வேர்க்கடலை"
        ],
        "answer": 2,
        "explanation": "ரொட்டிக் காளான் ஒரு பூவாத் தாவரம் (பூஞ்சை). இது ஸ்போர்கள் மூலம் இனப்பெருக்கம் செய்கிறது, விதைகளால் அல்ல."
      },
      {
        "question": "தாவரங்களை அவற்றின் ஆயுள்காலம், தண்டின் தன்மை தவிர வேறு எதன் அடிப்படையில் வகைப்படுத்தலாம்?",
        "options": [
          "பூக்கும் தன்மை",
          "நிறங்கள் (பச்சையம் உள்ளவை/அற்றவை)",
          "விதைகள்",
          "மேற்கூறிய அனைத்தும்"
        ],
        "answer": 3,
        "explanation": "தாவரங்கள் தண்டு, ஆயுள்காலம், விதைகள், பூக்கும் தன்மை மற்றும் பச்சையம் (நிறம்) ஆகியவற்றின் அடிப்படையில் வகைப்படுத்தப்படுகின்றன."
      },
      {
        "question": "அல்லிவட்டம் மற்றும் புல்லிவட்டம் ஆகிய இரண்டும் எதன் பாகங்கள் ஆகும்?",
        "options": [
          "இலை",
          "கனி",
          "மலர்",
          "வேர்"
        ],
        "answer": 2,
        "explanation": "புல்லிவட்டம், அல்லிவட்டம், மகரந்தத்தாள் மற்றும் சூலகம் ஆகிய நான்கும் மலரின் முக்கிய பாகங்கள் ஆகும்."
      },
      {
        "question": "சூலகம் மகரந்தத் துகள்களுடன் இணைந்து எதனை உருவாக்குகிறது?",
        "options": [
          "புதிய மலர்",
          "கனி (விதை)",
          "இலை",
          "ஸ்போர்கள்"
        ],
        "answer": 1,
        "explanation": "மலரின் பெண்பாகமான சூலகம் மகரந்த சேர்க்கைக்குப் பின் கனியாகவும், விதையாகவும் மாறுகிறது."
      },
      {
        "question": "உணவில் நறுமணப் பொருளாகப் பயன்படும் பூ எது?",
        "options": [
          "காலிபிளவர்",
          "வாழைப்பூ",
          "கிராம்பு (இலவங்கம்)",
          "சூரியகாந்தி"
        ],
        "answer": 2,
        "explanation": "கிராம்பு என்பது மரத்தில் பூக்கும் மலர் மொட்டாகும். இது சிறந்த நறுமணப் பொருளாகவும் மருந்தாகவும் பயன்படுகிறது."
      },
      {
        "question": "வாழ்க்கைச் சூழல் வினா: நீங்கள் மலைப்பிரதேசத்திற்கு செல்கிறீர்கள், அங்கு 12 ஆண்டுகளுக்கு ஒருமுறை ஒரு மலர் பூப்பதாகக் கூறுகிறார்கள். அது எந்த மலராக இருக்கும்?",
        "options": [
          "மணிப்பூ",
          "குறிஞ்சிப்பூ",
          "டாலியா",
          "ரஃப்ளேசியா"
        ],
        "answer": 1,
        "explanation": "குறிஞ்சிப்பூ தென்னிந்தியாவின் மலைப்பகுதிகளில் 12 வருடங்களுக்கு ஒருமுறை மட்டுமே பூக்கக்கூடிய அபூர்வ மலராகும்."
      },
      {
        "question": "கூற்று: அயல் தாவரங்கள் அனைத்தும் உணவுக்காக மட்டுமே வளர்க்கப்படுகின்றன. காரணம்: பார்த்தீனியம் ஒரு சிறந்த அயல் உணவுத் தாவரமாகும்.",
        "options": [
          "கூற்று சரி, காரணம் தவறு",
          "கூற்று தவறு, காரணம் சரி",
          "கூற்று மற்றும் காரணம் இரண்டும் சரி",
          "கூற்று மற்றும் காரணம் இரண்டும் தவறு"
        ],
        "answer": 3,
        "explanation": "அயல் தாவரங்கள் பெரும்பாலும் அலங்கார நோக்கங்களுக்காக வளர்க்கப்படுகின்றன. பார்த்தீனியம் ஒரு தீங்கு விளைவிக்கும் களைச்செடி, உணவுத் தாவரம் அல்ல."
      },
      {
        "question": "விசிறி வாழை மற்றும் கற்றாழை ஆகியவை எந்த வகை தாவரங்களுக்கு சிறந்த உதாரணம்?",
        "options": [
          "உணவுத் தாவரங்கள்",
          "அயல் / அழகு தாவரங்கள்",
          "பூவாத் தாவரங்கள்",
          "நீர்வாழ் தாவரங்கள்"
        ],
        "answer": 1,
        "explanation": "இவை இயல்பான இடத்திலிருந்து வீடுகள் மற்றும் பூங்காக்களில் அழகுக்காக வளர்க்கப்படும் அயல் தாவரங்கள் ஆகும்."
      },
      {
        "question": "மரவள்ளிக்கிழங்கு தாவரத்தின் எந்த பாகத்தில் அதிகப்படியான உணவை சேமிக்கிறது?",
        "options": [
          "தண்டு",
          "வேர்",
          "இலை",
          "கனி"
        ],
        "answer": 1,
        "explanation": "கேரட், பீட்ரூட், மரவள்ளிக்கிழங்கு ஆகியவை வேர்ப்பகுதியில் உணவை சேமிப்பதால் நாம் அதன் வேரை உண்கிறோம்."
      },
      {
        "question": "இஞ்சி தாவரத்தின் எந்தப் பகுதி நாம் பயன்படுத்தும் உணவாகும்?",
        "options": [
          "நிலத்தடி வேர்",
          "நிலத்தடி தண்டு",
          "இலை",
          "மலர்"
        ],
        "answer": 1,
        "explanation": "இஞ்சி, மஞ்சள், வெங்காயம், உருளைக்கிழங்கு ஆகியவை மாற்றுரு அடைந்த நிலத்தடி தண்டுகள் ஆகும்."
      },
      {
        "question": "நாம் பச்சையாக உண்ணக்கூடிய உணவுப் பொருள் பெரும்பாலும் தாவரத்தின் எந்தப் பாகமாக இருக்கும்?",
        "options": [
          "வேர்",
          "தண்டு",
          "பழங்கள் (கனிகள்)",
          "விதைகள்"
        ],
        "answer": 2,
        "explanation": "பெரும்பாலான பழங்களை நாம் சமைக்காமல் பச்சையாகவே உண்ணலாம். இவற்றில் உயிர்ச்சத்துகள் மற்றும் தாதுக்கள் நிறைந்துள்ளன."
      },
      {
        "question": "உயிர்ச்சத்துகள் (Vitamins) மற்றும் தாது உப்புகள் (Minerals) அதிக அளவில் எதில் காணப்படுகின்றன?",
        "options": [
          "விதைகள்",
          "தண்டுகள்",
          "பழங்கள் (கனிகள்)",
          "வேர்கள்"
        ],
        "answer": 2,
        "explanation": "பழங்களில் அதிக அளவு வைட்டமின்களும் தாது உப்புகளும் நிறைந்துள்ளதால் அவை உடல் ஆரோக்கியத்திற்கு மிகவும் உதவுகின்றன."
      },
      {
        "question": "ஒரு குறிப்பிட்ட பருவத்தில் மட்டும் பூக்கும் மலர்கள் எவ்வாறு அழைக்கப்படுகின்றன?",
        "options": [
          "வருடாந்திர மலர்கள்",
          "பருவகால மலர்கள்",
          "அயல் மலர்கள்",
          "உள்ளூர் மலர்கள்"
        ],
        "answer": 1,
        "explanation": "காலநிலை மாற்றங்களுக்கு ஏற்ப வசந்தகாலம், கோடைக்காலம், குளிர்காலம் என குறிப்பிட்ட பருவத்தில் மட்டும் பூப்பவை பருவகால மலர்கள் எனப்படும்."
      },
      {
        "question": "ஒப்புமை காண்க: முட்டைக்கோஸ் : இலை :: கரும்பு : ?",
        "options": [
          "வேர்",
          "தண்டு",
          "மலர்",
          "கனி"
        ],
        "answer": 1,
        "explanation": "முட்டைக்கோஸில் உணவானது இலையில் சேமிக்கப்படுகிறது. கரும்பில் இனிப்பான சாறு அதன் தண்டுப்பகுதியில் சேமிக்கப்படுகிறது."
      },
      {
        "question": "ஒப்புமை காண்க: மாமரம் : பூக்கும் தாவரம் :: பெரணி : ?",
        "options": [
          "பூக்கும் தாவரம்",
          "பூவாத் தாவரம்",
          "நீர் தாவரம்",
          "அயல் தாவரம்"
        ],
        "answer": 1,
        "explanation": "மாமரம் பூக்களை உருவாக்கும். பெரணி மலர்கள் இன்றி ஸ்போர்கள் மூலம் இனப்பெருக்கம் செய்யும் பூவாத் தாவரமாகும்."
      },
      {
        "question": "தாவரங்களின் சுவாசித்தலுக்கு உதவும் வாயுப்பரிமாற்றம் எதன் மூலம் நடைபெறுகிறது?",
        "options": [
          "இலை நுனி",
          "நரம்புகள்",
          "இலைத்துளைகள்",
          "இலைக்காம்பு"
        ],
        "answer": 2,
        "explanation": "இலையின் அடிப்பகுதியில் உள்ள மிகச்சிறிய இலைத்துளைகளே (Stomata) வாயுப்பரிமாற்றத்திற்கு உதவுகின்றன."
      },
      {
        "question": "சூரிய ஒளியின்றி தாவரத்தால் எதனை உற்பத்தி செய்ய இயலாது?",
        "options": [
          "நீர்",
          "கார்பன் டைஆக்ஸைடு",
          "உணவு",
          "வேர்கள்"
        ],
        "answer": 2,
        "explanation": "ஒளிச்சேர்க்கை என்ற பெயரிலேயே ஒளி உள்ளது. ஒளியின்றி தாவரத்தால் உணவு தயாரிக்க முடியாது."
      },
      {
        "question": "ரொட்டிக் காளான் (Bread mould) எந்த வகையைச் சேர்ந்தது?",
        "options": [
          "பச்சையம் உள்ள பாசிகள்",
          "பச்சையம் அற்ற பூஞ்சைகள்",
          "பூக்கும் ஒட்டுண்ணி",
          "தற்சார்பு உயிரி"
        ],
        "answer": 1,
        "explanation": "ரொட்டிக் காளான் என்பது பச்சையம் இல்லாததால் பிற உயிர்களை (ரொட்டியை) சார்ந்து வாழும் ஒரு வகை பூஞ்சை ஆகும்."
      },
      {
        "question": "பூக்கும் தன்மையின் அடிப்படையில் தாவரங்களை எத்தனை வகையாகப் பிரிக்கலாம்?",
        "options": [
          "இரண்டு",
          "மூன்று",
          "நான்கு",
          "ஐந்து"
        ],
        "answer": 0,
        "explanation": "பூக்கும் தன்மை அடிப்படையில் தாவரங்கள் பூக்கும் தாவரங்கள் மற்றும் பூவாத் தாவரங்கள் என இரண்டு வகையாகப் பிரிக்கப்படுகின்றன."
      },
      {
        "question": "பச்சையம் உள்ள தாவரங்களுக்கு மற்றொரு பெயர் என்ன?",
        "options": [
          "ஹெட்டிரோட்ரோப்கள்",
          "சாறுண்ணிகள்",
          "ஆட்டோட்ரோப்கள்",
          "சிதைப்பவைகள்"
        ],
        "answer": 2,
        "explanation": "தற்சார்பு உயிரினங்கள் ஆங்கிலத்தில் ஆட்டோட்ரோப்கள் (Autotrophs) என்று அழைக்கப்படுகின்றன."
      },
      {
        "question": "இனப்பெருக்கத்திற்கு உதவும் மகரந்தத் துகள்கள் மலரின் எப்பகுதியில் காணப்படுகின்றன?",
        "options": [
          "புல்லிவட்டம்",
          "அல்லிவட்டம்",
          "சூலகம்",
          "மகரந்தத்தாள்"
        ],
        "answer": 3,
        "explanation": "மலரின் ஆண் பாகமான மகரந்தத்தாளிலேயே மகரந்தத் துகள்கள் நிறைந்துள்ளன."
      },
      {
        "question": "மகரந்தச் சேர்க்கைக்கு உதவும் உயிரினங்கள் எவை?",
        "options": [
          "மண்புழுக்கள்",
          "பாம்புகள்",
          "தேனீக்கள் மற்றும் வண்ணத்துப்பூச்சிகள்",
          "மீன்கள்"
        ],
        "answer": 2,
        "explanation": "பூச்சிகளான தேனீக்கள் மற்றும் வண்ணத்துப்பூச்சிகள் தேனுக்காக அல்லிவட்டத்தால் ஈர்க்கப்பட்டு மகரந்தச் சேர்க்கைக்கு உதவுகின்றன."
      },
      {
        "question": "குளிர்கால மல்லிகை எந்தப் பருவத்தில் பூக்கும்?",
        "options": [
          "வசந்த காலம்",
          "கோடைக்காலம்",
          "குளிர்காலம்",
          "இலையுதிர் காலம்"
        ],
        "answer": 2,
        "explanation": "பெயரிலேயே உள்ளவாறு குளிர்கால மல்லிகை குளிர்காலத்தில் மட்டுமே பூக்கும் பருவகால மலராகும்."
      },
      {
        "question": "சைக்கஸ் (சாகோ பனை) என்பது எவ்வகை தாவரம்?",
        "options": [
          "உணவு தானியம்",
          " களைச்செடி",
          "அலங்கார / அயல் தாவரம்",
          "மருத்துவத் தாவரம்"
        ],
        "answer": 2,
        "explanation": "சைக்கஸ் என்பது வீடுகள் மற்றும் பூங்காக்களில் அழகுக்காக வளர்க்கப்படும் ஒரு அயல் தாவரமாகும்."
      },
      {
        "question": "பருப்பு வகைகள் மற்றும் பயறு வகைகள் ஆகியவை தாவரத்தின் எந்தப் பகுதியாகும்?",
        "options": [
          "கனிகள்",
          "விதைகள்",
          "பூக்கள்",
          "வேர்கள்"
        ],
        "answer": 1,
        "explanation": "நாம் உண்ணும் துவரம் பருப்பு, உளுந்து, பாசிப்பயறு போன்றவை அனைத்தும் விதைகளாகும்."
      },
      {
        "question": "சரியா தவறா: காற்றில் உள்ள கார்பன் டைஆக்ஸைடு வேர்கள் மூலமாக உறிஞ்சப்படுகிறது.",
        "options": [
          "சரி",
          "தவறு",
          "பகுதி சரி",
          "இரண்டும்"
        ],
        "answer": 1,
        "explanation": "தவறு. காற்றில் உள்ள கார்பன் டைஆக்ஸைடு இலைகளில் உள்ள இலைத்துளைகள் வழியாகவே உறிஞ்சப்படுகிறது. வேர்கள் நீரை மட்டுமே உறிஞ்சுகின்றன."
      },
      {
        "question": "உணவு தயாரித்தலின் போது இலைகளில் சேமிக்கப்படும் ஆற்றல் மூலப்பொருள் எது?",
        "options": [
          "ஆக்ஸிஜன்",
          "கார்பன் டைஆக்ஸைடு",
          "உணவு (ஸ்டார்ச்)",
          "நீர்"
        ],
        "answer": 2,
        "explanation": "ஒளிச்சேர்க்கையின் போது உருவாகும் உணவு தாவரத்தின் பல்வேறு பகுதிகளில் சேமிக்கப்படுகிறது."
      },
      {
        "question": "தாவரத்தின் பெண் பாகமான சூலகம் மலரின் எப்பகுதியில் அமைந்துள்ளது?",
        "options": [
          "வெளிப்புற அடுக்கில்",
          "அல்லிவட்டத்தின் மேல்",
          "நடுப்பகுதியில்",
          "காம்பின் அடியில்"
        ],
        "answer": 2,
        "explanation": "சூலகம் என்பது மலரின் மையத்தில் அல்லது நடுப்பகுதியில் பாதுகாப்பாக அமைந்துள்ள பெண் பாகமாகும்."
      },
      {
        "question": "பொருத்துக: \n1. டிசம்பர் பூ - அ. அனைத்துப் பருவமும் \n2. ரோஜா - ஆ. குளிர்காலம் \n3. டாலியா - இ. கோடைக்காலம் \n4. கனகாம்பரம் - ஈ. இலையுதிர் காலம்",
        "options": [
          "1-ஆ, 2-இ, 3-ஈ, 4-அ",
          "1-இ, 2-ஆ, 3-அ, 4-ஈ",
          "1-அ, 2-ஈ, 3-இ, 4-ஆ",
          "1-ஈ, 2-அ, 3-ஆ, 4-இ"
        ],
        "answer": 0,
        "explanation": "டிசம்பர் பூ-குளிர்காலம், ரோஜா-கோடைக்காலம், டாலியா-இலையுதிர் காலம், கனகாம்பரம்-அனைத்துப் பருவம்."
      },
      {
        "question": "பொருத்துக: \n1. பச்சையம் அற்ற தாவரம் - அ. நெல் \n2. பச்சையம் உள்ள தாவரம் - ஆ. காளான் \n3. பூக்கும் தாவரம் - இ. பெரணி \n4. பூவாத் தாவரம் - ஈ. மா",
        "options": [
          "1-ஆ, 2-அ, 3-ஈ, 4-இ",
          "1-அ, 2-ஆ, 3-இ, 4-ஈ",
          "1-ஈ, 2-இ, 3-ஆ, 4-அ",
          "1-இ, 2-ஈ, 3-அ, 4-ஆ"
        ],
        "answer": 0,
        "explanation": "காளான் பச்சையமற்றது. நெல் பச்சையமுள்ளது. மா பூக்கும் தாவரம். பெரணி பூவாத் தாவரம்."
      },
      {
        "question": "இலையின் முனைப்பகுதி _________ ஆகும்.",
        "options": [
          "இலைத்தாள்",
          "இலை நுனி",
          "மைய நரம்பு",
          "நரம்புகள்"
        ],
        "answer": 1,
        "explanation": "இலையின் கூர்மையான முனையை இலை நுனி என்று அழைக்கிறோம்."
      },
      {
        "question": "பின்வருவனவற்றில் எது முதன்மை உற்பத்தியாளர்?",
        "options": [
          "தாவரம்",
          "விலங்கு",
          "மனிதன்",
          "மேற்கூறிய எதுவும் இல்லை"
        ],
        "answer": 0,
        "explanation": "தாவரங்கள் மட்டுமே தங்களுக்கான உணவை தாங்களே தயாரித்து மற்ற உயிர்களுக்கும் உணவளிப்பதால் அவை முதன்மை உற்பத்தியாளர்கள்."
      },
      {
        "question": "குளிர்காலத்தில் மட்டுமே மலரும் மலர் எது?",
        "options": [
          "மல்லிகை",
          "மணிப்பூ",
          "டிசம்பர் பூ",
          "கனகாம்பரம்"
        ],
        "answer": 2,
        "explanation": "டிசம்பர் பூ பெயருக்கு ஏற்றாற்போல குளிர்காலத்தில் மட்டுமே பூக்கும் மலராகும்."
      },
      {
        "question": "அலங்காரத் தாவரத்தைத் தேர்ந்தெடுத்து எழுதுக.",
        "options": [
          "பார்த்தீனியம்",
          "மாங்காய்",
          "விசிறி வாழை",
          "நிலக்கடலை"
        ],
        "answer": 2,
        "explanation": "விசிறி வாழை அதன் அழகான தோற்றத்திற்காக வளர்க்கப்படும் அலங்காரத் தாவரமாகும்."
      },
      {
        "question": "பின்வருவனவற்றுள் எந்தத் தாவரத்தின் மலர் உண்ணக் கூடியது?",
        "options": [
          "காலிபிளவர்",
          "உருளைக்கிழங்கு",
          "புதினா",
          "முட்டைக்கோஸ்"
        ],
        "answer": 0,
        "explanation": "காலிபிளவர் என்பது தாவரத்தின் மலர் பகுதியாகும், உருளை-தண்டு, புதினா/முட்டைக்கோஸ்-இலைகள்."
      },
      {
        "question": "ஒளிச்சேர்க்கையின் போது _________ உற்பத்தி செய்யப்பட்டு இலையில் சேமிக்கப்படுகிறது.",
        "options": [
          "நீர்",
          "தாது உப்பு",
          "உணவு (கார்போஹைட்ரேட்)",
          "சூரிய ஒளி"
        ],
        "answer": 2,
        "explanation": "ஒளிச்சேர்க்கை மூலம் உணவு தயாரிக்கப்பட்டு தாவரத்தின் பல்வேறு பகுதிகளில் சேமிக்கப்படுகிறது."
      },
      {
        "question": "பசுந்தாவரங்கள் _________ நிறமியை கொண்டுள்ளன.",
        "options": [
          "மெலனின்",
          "பச்சையம் (குளோரோபில்)",
          "கரோட்டின்",
          "சாந்தோபில்"
        ],
        "answer": 1,
        "explanation": "தாவரங்கள் பச்சையாக இருக்கக் காரணமான நிறமி பச்சையம் (Chlorophyll) ஆகும்."
      },
      {
        "question": "வெங்காயம் தாவரத்தின் எந்தப் பகுதியாகும்?",
        "options": [
          "வேர்",
          "தண்டு",
          "இலை",
          "மலர்"
        ],
        "answer": 1,
        "explanation": "வெங்காயம், உருளைக்கிழங்கு ஆகியவை நிலத்தடித் தண்டுப் பகுதிகளாகும்."
      },
      {
        "question": "மலரின் ஆண் பகுதி _________ ஆகும்.",
        "options": [
          "சூலகம்",
          "புல்லிவட்டம்",
          "அல்லிவட்டம்",
          "மகரந்தத்தாள்"
        ],
        "answer": 3,
        "explanation": "மகரந்தத்தாள் என்பது மகரந்தங்களைக் கொண்ட ஆண் இனப்பெருக்க உறுப்பாகும்."
      },
      {
        "question": "உணவாகப் பயன்படும் விதைக்கு ஓர் எடுத்துக்காட்டு தருக.",
        "options": [
          "காலிபிளவர்",
          "கேரட்",
          "வெந்தயம்",
          "முட்டைக்கோஸ்"
        ],
        "answer": 2,
        "explanation": "வெந்தயம், அரிசி, பருப்பு வகைகள் ஆகியவை நாம் உண்ணும் விதைகளாகும்."
      },
      {
        "question": "மலரானது மொட்டாக இருக்கும்போது அதனைப் பாதுகாப்பது எது?",
        "options": [
          "சூலகம்",
          "அல்லிவட்டம்",
          "புல்லிவட்டம்",
          "இலை"
        ],
        "answer": 2,
        "explanation": "புல்லிவட்டம் என்பது மொட்டை மூடிப் பாதுகாக்கும் வெளிப்பகுதியாகும்."
      },
      {
        "question": "மகரந்தத்தாள் வட்டத்தில் எவை நிரம்பியுள்ளன?",
        "options": [
          "தேன்",
          "மகரந்தத் துகள்கள்",
          "விதைகள்",
          "ஸ்போர்கள்"
        ],
        "answer": 1,
        "explanation": "மகரந்தத்தாள் வட்டத்தில் இனப்பெருக்கத்திற்கு உதவும் மகரந்தத் துகள்கள் உள்ளன."
      },
      {
        "question": "சூலகம் என்பது மலரின் எந்தப் பகுதியாகும்?",
        "options": [
          "ஆண் பகுதி",
          "பெண் பகுதி",
          "கவர்ச்சிப் பகுதி",
          "பாதுகாப்புப் பகுதி"
        ],
        "answer": 1,
        "explanation": "சூலகம் என்பது மலரின் பெண் பாகமாகும். இதுவே கனியாக மாறுகிறது."
      },
      {
        "question": "உணவாகப் பயன்படும் இலைக்கு ஓர் எடுத்துக்காட்டு தருக.",
        "options": [
          "முருங்கைக்கீரை",
          "உருளைக்கிழங்கு",
          "கரும்பு",
          "பீட்ரூட்"
        ],
        "answer": 0,
        "explanation": "முருங்கைக்கீரை, கொத்தமல்லி, முட்டைக்கோஸ் ஆகியவை உணவாகும் இலைகள்."
      }
    ]
  },
  "material": {
    "sections": [
      {
        "title": "பாடக்கருத்துக்கள்",
        "type": "infobox",
        "content": [
          {
            "text": "I. இலையின் பாகங்கள்:\nதாவரங்கள் தங்கள் உணவை இலையில் உள்ள பச்சையம் (குளோரோபில்) உதவியுடன் தாங்களே தயாரிக்கின்றன. இலையின் முக்கிய பாகங்கள்:\n1. இலைத்தாள் (லாமினா) - பரந்த தட்டையான பகுதி.\n2. இலை நுனி - இலையின் முனைப் பகுதி.\n3. மைய நரம்பு - இலையின் நடுவில் செல்வது.\n4. நரம்புகள் - மைய நரம்பிலிருந்து பிரியும் கிளைகள், இவை நீர் மற்றும் தாதுக்களைக் கொண்டு செல்லும் வெற்றுக்குழாய்கள்.\n5. இலைக்காம்பு - இலையைத் தண்டுடன் இணைக்கும் பகுதி.\n\nஒளிச்சேர்க்கை:\nசூரிய ஒளியின் முன்னிலையில் பச்சையம், நீர், கார்பன் டைஆக்ஸைடு ஆகியவற்றைப் பயன்படுத்தி தாவரங்கள் உணவு தயாரிக்கும் முறை. (சூரிய ஒளி + நீர் + கார்பன் டைஆக்ஸைடு -> உணவு + ஆக்ஸிஜன்). தாவரங்கள் 'முதன்மை உற்பத்தியாளர்கள்' எனப்படுகின்றன.\n\nII. தாவரங்களின் வகைப்பாடு:\nபூக்கும் தன்மையின் அடிப்படையில் 2 வகை:\n1. பூக்கும் தாவரங்கள்: மலர்களால் விதைகளை உருவாக்கி இனப்பெருக்கம் செய்கின்றன (எ.கா: மா, வேம்பு, நெல்).\n2. பூவாத் தாவரங்கள்: மலர்கள் இன்றி ஸ்போர்கள் மூலம் இனப்பெருக்கம் செய்கின்றன (எ.கா: பாசிகள், பூஞ்சைகள், பெரணி).\n\nநிறத்தின் அடிப்படையில் 2 வகை:\n1. பச்சையம் உள்ள தாவரங்கள் (ஆட்டோட்ரோப்கள் / தற்சார்பு): தாங்களே உணவு தயாரிப்பவை (எ.கா: புல், நெல்).\n2. பச்சையம் அற்ற தாவரங்கள் (ஹெட்டிரோட்ரோப்கள் / பிறசார்பு): மற்ற உயிரினங்களை சார்ந்திருப்பவை (எ.கா: காளான், ரொட்டிக் காளான்).\n\nIII. மலரின் பாகங்கள்:\n1. புல்லிவட்டம்: மொட்டைப் பாதுகாக்கும் பச்சை நிற அடுக்கு.\n2. அல்லிவட்டம்: பூச்சிகளை ஈர்க்கும் பிரகாசமான அடுக்கு.\n3. மகரந்தத்தாள்: மகரந்தத் துகள்களைக் கொண்ட மலரின் ஆண் பாகம்.\n4. சூலகம்: கனியாக மாறும் மலரின் பெண் பாகம்.\n\nபருவகால மலர்கள்: குளிர்காலம் (டிசம்பர் பூ, சம்பங்கி), கோடைக்காலம் (மல்லிகை, சூரியகாந்தி, ரோஜா), இலையுதிர்/வசந்த காலம் (டாலியா, குங்குமப்பூ, மணிப்பூ).\n\nIV. அயல் தாவரங்கள் (அழகு தாவரங்கள்):\nமனிதர்களால் தற்செயலாகவோ அழகுக்காகவோ ஓரிடத்திலிருந்து கொண்டுவரப்பட்டவை. (எ.கா: சைக்கஸ், பெரணி, குரோட்டன்ஸ், விசிறி வாழை, கற்றாழை).\n\nV. உணவாகும் தாவரங்கள்:\nவேர்கள் - கேரட், பீட்ரூட், மரவள்ளிக்கிழங்கு.\nதண்டுகள் - வெங்காயம், உருளைக்கிழங்கு, இஞ்சி, மஞ்சள், கரும்பு.\nஇலைகள் - முட்டைக்கோஸ், கொத்தமல்லி, முருங்கைக்கீரை.\nபூக்கள் - வாழைப்பூ, காலிபிளவர், கிராம்பு.\nபழங்கள் - மா, பலா, வாழைப்பழம்.\nதானியங்கள்/விதைகள் - அரிசி, வெந்தயம், பருப்பு வகைகள்."
          }
        ]
      },
      {
        "title": "உங்களுக்கு தெரியுமா? / கூடுதல் தகவல்கள்",
        "type": "infobox",
        "content": [
          {
            "text": "- கள்ளிச்செடி போன்ற தாவரங்களில் இலைகள் இல்லை. அவை தமது பச்சையான தண்டுகள் மூலமாக உணவைத் தயாரிக்கின்றன.\n- உலகின் மிகப் பெரிய மலர் 'ரஃப்ளேசியா' ஆகும். இது இந்தோனேசியாவின் மழைக்காடுகளில் காணப்படுகிறது.\n- கனகாம்பரம் அனைத்துப் பருவங்களிலும் மலரும் மலராகும்.\n- குறிஞ்சிப் பூ 12 ஆண்டுகளுக்கு ஒருமுறை மட்டுமே மலரும்.\n- பார்த்தீனியம் என்பது ஒருவகை களைச்செடி. இதன் மகரந்தத் துகள்கள் இயற்கையிலேயே ஒவ்வாமை (Allergy) கொண்டவை. இதைத் தொடாமல் இருப்பது நல்லது.\n- பூமியில் அதிக நாள் வாழும் உயிரினம் மரங்கள் ஆகும்.\n- மூங்கில் மரங்கள் ஒரு நாளில் 90 சென்டிமீட்டர் அளவு வளரக்கூடியவை."
          }
        ]
      },
      {
        "title": "கலைச்சொற்கள்",
        "type": "infobox",
        "content": [
          {
            "text": "- பச்சையம் (Chlorophyll): தாவரங்கள் உணவு தயாரிக்க உதவும் பச்சை நிறமி.\n- இலைத்துளைகள் (Stomata): இலைகளின் அடிப்பகுதியில் உள்ள சிறிய துளைகள். வாயுப்பரிமாற்றத்திற்கு உதவுகின்றன.\n- ஒளிச்சேர்க்கை (Photosynthesis): தாவரங்கள் உணவு தயாரிக்கும் முறை.\n- ஆட்டோட்ரோப்கள் (Autotrophs): தமக்குத் தேவையான உணவை தாமே தயாரிக்கும் தற்சார்பு தாவரங்கள்.\n- ஹெட்டிரோட்ரோப்கள் (Heterotrophs): உணவுக்காக மற்றவர்களை சார்ந்து வாழும் பிறசார்பு தாவரங்கள்."
          }
        ]
      },
      {
        "title": "பாடச்சுருக்கம்",
        "type": "infobox",
        "content": [
          {
            "text": "அனைத்து உயிரினங்களும் உணவை உட்கொள்கின்றன. தாவரங்கள் இலையில் இருக்கும் பச்சையம் உதவியுடன் தமக்குத் தேவையான உணவை தாங்களே தயாரிக்கின்றன (ஒளிச்சேர்க்கை). இதனால் இவை முதன்மை உற்பத்தியாளர்கள் எனப்படுகின்றன. இலை பல்வேறு பாகங்களைக் கொண்டுள்ளது. தாவரங்கள் பூக்கும் தன்மை மற்றும் பச்சையம் உள்ளதா என்பதன் அடிப்படையில் வகைப்படுத்தப்படுகின்றன. மலரானது புல்லிவட்டம், அல்லிவட்டம், மகரந்தத்தாள் மற்றும் சூலகம் ஆகிய பாகங்களைக் கொண்டுள்ளது. சில தாவரங்கள் அழகுக்காக அயல் நாடுகளிலிருந்து கொண்டுவரப்படுகின்றன. தாவரங்களின் வேர், தண்டு, இலை, பூ, பழம் மற்றும் விதைகள் என பல பாகங்கள் நமக்கு உணவாகப் பயன்படுகின்றன."
          }
        ]
      },
      {
        "title": "படக்குறிப்புகள்",
        "type": "infobox",
        "content": [
          {
            "text": "- இலைத்துளைகள்: இலையின் அடிப்பகுதியில் உருப்பெருக்கியால் பார்க்கும்போது நுண்ணிய துளைகளாகத் தெரிகின்றன.\n- ஒளிச்சேர்க்கை: சூரிய ஒளியின் முன்னிலையில் தாவரம் கார்பன் டைஆக்ஸைடை உள்ளிழுத்து ஆக்ஸிஜனை வெளியிடுகிறது.\n- இருட்டறைச் செடி: பெட்டியில் வைக்கப்பட்ட செடி சூரிய ஒளி இன்றி வாடி நிறம் மாறி காணப்படுகிறது.\n- காளான்: இவை பச்சையம் அற்ற தாவரங்கள், மட்கிய பொருட்களின் மீது வளர்கின்றன.\n- மலரின் பாகங்கள்: மலரின் நடுவில் சூலகமும், அதைச் சுற்றி மகரந்தத்தாளும் உள்ளன. வெளிப்புறத்தில் வண்ணமயமான அல்லிவட்டமும், கீழே பச்சை நிற புல்லிவட்டமும் உள்ளன."
          }
        ]
      },
      {
        "title": "பாட பின்புற வினாக்கள் (ஒரு மதிப்பெண்)",
        "type": "infobox",
        "content": [
          {
            "text": "சரியான விடையைத் தேர்ந்தெடுத்து எழுதுக:\n1. இலையின் முனைப்பகுதி - இலை நுனி ஆகும்.\n2. முதன்மை உற்பத்தியாளர் - தாவரம்.\n3. குளிர்காலத்தில் மட்டுமே மலரும் மலர் - டிசம்பர் பூ.\n4. அலங்காரத் தாவரம் - விசிறி வாழை.\n5. மலர் உண்ணக் கூடிய தாவரம் - காலிபிளவர்.\n\nகோடிட்ட இடங்களை நிரப்புக:\n1. ஒளிச்சேர்க்கையின் போது 'உணவு' உற்பத்தி செய்யப்பட்டு இலையில் சேமிக்கப்படுகிறது.\n2. பசுந்தாவரங்கள் 'பச்சையம்' நிறமியை கொண்டுள்ளன.\n3. வெங்காயம் தாவரத்தின் 'தண்டு' பகுதியாகும்.\n4. மலரின் ஆண் பகுதி 'மகரந்தத்தாள்' ஆகும்.\n5. உணவாகப் பயன்படும் விதைக்கு ஓர் எடுத்துக்காட்டு 'வெந்தயம் / பருப்பு வகைகள்'.\n\nஓரிரு வார்த்தையில் விடையளி:\n1. தாவரத்தின் பெண் பகுதி எது? - சூலகம்.\n2. உணவாகப் பயன்படும் இலை - முருங்கைக்கீரை (அல்லது முட்டைக்கோஸ்).\n3. உணவில் நறுமணப் பொருளாகப் பயன்படும் பூ - கிராம்பு.\n4. விதைகளில் காணப்படும் சத்துகள் - கார்போஹைட்ரேட் மற்றும் புரதங்கள்.\n5. கோடைக்காலத்தில் பூக்கும் மலர் - மல்லிகை (அல்லது ரோஜா, சூரியகாந்தி)."
          }
        ]
      }
    ]
  }
}