{
  "lesson_meta": {
    "title": "யானைக்கும் பானைக்கும் சரி",
    "unit": 3,
    "grade": "4",
    "term": "2",
    "subject": "Tamil",
    "code": "tam_4_t2_l5"
  },
  "material": {
    "sections": [
      {
        "title": "1. பாடச் சுருக்கம்",
        "content": "<div style='background: #fdf4ff; border-left: 5px solid #d946ef; padding: 1.5rem; border-radius: 0.75rem; line-height: 1.8; color: #701a75;'><p>மரியாதை இராமன் ஒருமுறை ஒரு விசித்திரமான வழக்கை எதிர்கொண்டார். உழவர் ஒருவர் தன் மகனின் திருமண ஊர்வலத்திற்காக அரபு வணிகரிடம் யானையை இரவல் கேட்டார். ஊர்வலத்தின் போது யானை தற்செயலாக இறந்துவிட்டது. உழவர் அதற்கு மாற்றாகப் பணமோ அல்லது வேறு யானையோ தருவதாகக் கூறினார். ஆனால் வணிகர் பிடிவாதமாக 'இறந்துபோன அதே யானைதான் வேண்டும்' என்று அடம்பிடித்தார்.</p></div>"
      },
      {
        "title": "2. மரியாதை இராமனின் தந்திரம்",
        "content": "<div style='background: #f8fafc; border: 1px solid #e2e8f0; padding: 1.5rem; border-radius: 0.75rem; line-height: 1.8;'><p>மரியாதை இராமன் உழவருக்கு ஒரு திட்டம் வகுத்துக் கொடுத்தார். உழவர் தன் வீட்டின் கதவுக்குப் பின்னால் பழைய பானைகளை அடுக்கி வைத்துவிட்டு, கதவைத் தாழ்ப்பாள் போடாமல் மூடி வைத்தார். ஆத்திரத்துடன் வந்த வணிகர் கதவை வேகமாகத் தள்ள, பின்னாலிருந்த பழைய பானைகள் உடைந்து நொறுங்கின. உடனே உழவர், 'காலங்காலமாகப் போற்றி வைத்திருந்த தன் பழைய பானைகளை அதே போல் திருப்பித் தர வேண்டும்' என்று சண்டையிட்டார்.</p></div>"
      },
      {
        "title": "3. இறுதித் தீர்ப்பு",
        "content": "<div style='background: #f0fdfa; border-left: 5px solid #14b8a6; padding: 1.5rem; border-radius: 0.75rem; line-height: 1.8;'><p>நீதிமன்றத்தில் மரியாதை இராமன் வணிகரிடம், 'நீங்கள் உடைத்த பானைகளைத் திருப்பித் தந்துவிட்டால், உழவரும் உங்கள் யானையைத் திருப்பித் தந்துவிடுவார்' என்று தீர்ப்பளித்தார். வணிகர் தம்மால் பழைய பானைகளைத் தர முடியாது எனத் ஒப்புக்கொண்டார். உடனே மரியாதை இராமன், 'உம்மாலேயே திருப்பித் தரமுடியாது என்றால் உழவரால் மட்டும் எப்படித் திருப்பித் தரமுடியும்? ஆதலால் <b>யானைக்கும் பானைக்கும் சரியாகப் போய்விட்டது</b>' எனத் தீர்ப்பளித்தார்.</p><p style='margin-top: 1rem; font-weight: 600; color: #0f766e;'>நீதி: ஆத்திரக்காரனுக்குப் புத்தி மட்டு.</p></div>"
      },
      {
        "title": "4. அகராதி மற்றும் குறிப்புகள்",
        "content": "<div style='background: #fffbeb; border: 1px solid #f59e0b; padding: 1.5rem; border-radius: 0.75rem;'><ul style='line-height: 1.8;'><li>✅ <b>தற்செயலாக:</b> எதிர்பாராமல்</li><li>✅ <b>இரவல்:</b> திரும்பித் தரும் நிபந்தனையுடன் வாங்குதல்</li><li>✅ <b>காலங்காலமாக:</b> நீண்ட காலமாக / தொன்றுதொட்டு</li><li>✅ <b>விசித்திரமான:</b> புதுமையான / வினோதமான</li></ul></div>"
      },
      {
        "title": "5. சொல்லும் பொருளும் - ஒரு மதிப்பெண்",
        "content": "<div style='background: #f9fafb; border: 1px solid #d1d5db; padding: 1.5rem; border-radius: 0.75rem;'><ul style='line-height: 1.8;'><li>வணிகர் எந்த நாட்டைச் சேர்ந்தவர்? - <b>அரபு நாடு</b></li><li>யானையை இரவல் கேட்டவர் - <b>உழவர்</b></li><li>வழக்கை விசாரித்தவர் - <b>மரியாதை இராமன்</b></li><li>உழவர் வீட்டில் உடைந்தது - <b>பழைய பானைகள்</b></li></ul></div>"
      }
    ]
  },
  "quiz": {
    "questions": [
      {
        "question": "'யானைக்கும் பானைக்கும் சரி' என்ற கதையில் வழக்கை விசாரித்தவர் யார்?",
        "options": ["அரபு வணிகர்", "உழவர்", "மரியாதை இராமன்", "ஊர் தலைவர்"],
        "answer": 2,
        "explanation": "மரியாதை இராமன் இந்த விசித்திரமான வழக்கை எதிர்கொண்டு தீர்ப்பு வழங்கினார்."
      },
      {
        "question": "உழவர் யார் மீது வழக்கு தொடரப்பட்டார்?",
        "options": ["அரபு வணிகர் மீது", "அரபு வணிகர் உழவர் மீது", "மரியாதை இராமன் மீது", "ஊர் மக்கள் மீது"],
        "answer": 1,
        "explanation": "அரபு வணிகர் ஒருவர் உழவர் மீது தொடுத்த வழக்கு இது."
      },
      {
        "question": "உழவர் யானையை எதற்காக இரவல் கேட்டார்?",
        "options": ["விவசாயம் செய்ய", "பாரம் சுமக்க", "மகன் திருமண ஊர்வலத்திற்காக", "கோவில் திருவிழாவிற்காக"],
        "answer": 2,
        "explanation": "தம் மகன் திருமண விழாவில் ஊர்வலம் விடுவதற்காக உழவர் யானையை இரவல் கேட்டார்."
      },
      {
        "question": "வணிகர் எந்த நாட்டைச் சேர்ந்தவர்?",
        "options": ["சீன நாடு", "அரபு நாடு", "தமிழ்நாடு", "ரோமாபுரி"],
        "answer": 1,
        "explanation": "பாடப்பகுதியில் அவர் 'அரபு வணிகர்' என்று குறிப்பிடப்பட்டுள்ளார்."
      },
      {
        "question": "திருமண ஊர்வலத்தின் போது யானைக்கு என்ன நேர்ந்தது?",
        "options": ["ஓடிவிட்டது", "திருடு போனது", "தற்செயலாக இறந்துவிட்டது", "மதம் பிடித்தது"],
        "answer": 2,
        "explanation": "ஊர்வலத்தில் யானை தற்செயலாக (எதிர்பாராமல்) இறந்துவிட்டது."
      },
      {
        "question": "யானை இறந்தவுடன் உழவர் வணிகரிடம் என்ன தருவதாகக் கூறினார்?",
        "options": ["விலையோ அல்லது வேறு யானையோ", "நிலம்", "பொற்காசுகள்", "எதுவும் தரமுடியாது என்றார்"],
        "answer": 0,
        "explanation": "இறந்த யானைக்குப் பதிலாக அதன் விலையையோ அல்லது வேறு யானையோ வாங்கித் தருவதாக உழவர் கூறினார்."
      },
      {
        "question": "வணிகர் உழவரின் கோரிக்கையை ஏற்றுக்கொண்டாரா?",
        "options": ["ஏற்றுக்கொண்டார்", "பாதி மட்டும் ஏற்றுக்கொண்டார்", "ஏற்றுக்கொள்ள மறுத்தார்", "பணம் மட்டும் வாங்கிக்கொண்டார்"],
        "answer": 2,
        "explanation": "வணிகர் உழவரின் நியாயமான கோரிக்கையை ஏற்றுக்கொள்ள மறுத்தார்."
      },
      {
        "question": "வணிகர் எதற்காக அடம்பிடித்தார்?",
        "options": ["கூடுதல் பணம் வேண்டும் என்று", "வேறு யானை வேண்டும் என்று", "இறந்துபோன அதே யானைதான் வேண்டும் என்று", "உழவரைத் தண்டிக்க வேண்டும் என்று"],
        "answer": 2,
        "explanation": "வணிகர் இறந்துபோன அதே யானைதான் வேண்டுமென அடம்பிடித்தார்."
      },
      {
        "question": "உண்மையை உணர்ந்த மரியாதை இராமன் இருவரையும் எங்கு வரச் சொன்னார்?",
        "options": ["காவல் நிலையத்திற்கு", "நீதிமன்றத்திற்கு", "அரண்மனைக்கு", "ஊர் மந்தைக்கு"],
        "answer": 1,
        "explanation": "நீதிமன்றத்திற்கு நாளை வருமாறு இருவரையும் அனுப்பினார்."
      },
      {
        "question": "மரியாதை இராமன் யாரை மட்டும் தனியே அழைத்து ஆலோசனை கூறினார்?",
        "options": ["வணிகரை", "பார்வையாளரை", "உழவரை", "யாரையும் அழைக்கவில்லை"],
        "answer": 2,
        "explanation": "உழவரை மட்டும் தனியே அழைத்து ஒரு தந்திரமான திட்டத்தைக் கூறினார்."
      },
      {
        "question": "உழவரை நீதிமன்றத்திற்கு அழைத்து வர யார் வருவார் என மரியாதை இராமன் கூறினார்?",
        "options": ["காவலர்கள்", "அரபு வணிகர்", "மரியாதை இராமனே வருவார்", "ஊர் மக்கள்"],
        "answer": 1,
        "explanation": "உழவரை அழைக்க வணிகரை அவர் வீட்டிற்கு அனுப்புவதாகக் கூறினார்."
      },
      {
        "question": "உழவர் தன் வீட்டு கதவிற்குப் பின் எதை அடுக்கி வைக்க வேண்டும் என அறிவுறுத்தப்பட்டது?",
        "options": ["மூட்டைகளை", "பழைய பானைகளை", "மரக்கட்டைகளை", "புதிய பானைகளை"],
        "answer": 1,
        "explanation": "கதவிற்குப் பின்னால் பழைய பானைகளை அடுக்கி வைக்கச் சொன்னார்."
      },
      {
        "question": "கதவை எப்படி வைத்திருக்க வேண்டும் என உழவருக்கு கூறப்பட்டது?",
        "options": ["பூட்டி வைக்க வேண்டும்", "தாழ்ப்பாள் போட்டு வைக்க வேண்டும்", "தாழ்ப்பாள் போடாமல் வைத்திருக்க வேண்டும்", "முழுவதுமாக திறந்து வைத்திருக்க வேண்டும்"],
        "answer": 2,
        "explanation": "கதவைத் தாழ்ப்பாள் போடாமல் மூடி வைத்திருக்கச் சொன்னார்."
      },
      {
        "question": "வணிகர் உழவர் வீட்டிற்கு வந்தபோது எவ்வாறு கதவைத் தட்டினார்?",
        "options": ["மெதுவாக", "ஆத்திரத்துடன்", "தயக்கத்துடன்", "அன்பாக"],
        "answer": 1,
        "explanation": "வணிகர் ஆத்திரத்துடன் உழவர் வீட்டு கதவைத் தள்ளினார் (தட்டினார்)."
      },
      {
        "question": "கதவு வேகமாகத் திறந்துகொண்டதால் என்ன நிகழ்ந்தது?",
        "options": ["உழவர் கீழே விழுந்தார்", "கதவு உடைந்தது", "பானைகள் கீழே விழுந்து உடைந்து நொறுங்கின", "வணிகர் அடிபட்டார்"],
        "answer": 2,
        "explanation": "கதவின் பின்னிருந்த பழைய பானைகள் கீழே விழுந்து நொறுங்கின."
      },
      {
        "question": "உடைந்த பானைகள் எப்படிப்பட்டவை என்று உழவர் கூறினார்?",
        "options": ["நேற்று வாங்கியவை", "காலங்காலமாகப் போற்றி வைத்திருந்த பழம்பானைகள்", "விலை உயர்ந்த பானைகள்", "தங்கப் பானைகள்"],
        "answer": 1,
        "explanation": "தாம் காலங்காலமாகப் போற்றி வைத்திருந்த பானைகள் என்று உழவர் கூறினார்."
      },
      {
        "question": "உழவர் வணிகரிடம் எதைத் திருப்பித் தரும்படி கேட்டார்?",
        "options": ["பணம்", "புதிய பானைகள்", "இதே பழைய பானைகள்", "யானை"],
        "answer": 2,
        "explanation": "உடைந்த அதே பழைய பானைகளைத் திருப்பித் தரும்படி உழவர் அடம்பிடித்தார்."
      },
      {
        "question": "உழவர் கோபமாகக் கத்தியதைக் கண்ட வணிகரின் நிலை என்ன?",
        "options": ["சிரித்தார்", "எதிர்த்து சண்டையிட்டார்", "செய்வதறியாது திகைத்தார்", "அழுதுவிட்டார்"],
        "answer": 2,
        "explanation": "வணிகர் செய்வதறியாது திகைத்து நின்றார்."
      },
      {
        "question": "உழவர் வீட்டில் நடந்ததை நீதிமன்றத்தில் கூறியவர் யார்?",
        "options": ["உழவர்", "வணிகர்", "பக்கத்து வீட்டுக்காரர்", "காவலாளி"],
        "answer": 1,
        "explanation": "வணிகர் நீதிமன்றத்தில் நடந்தவற்றைத் தெரிவித்தார்."
      },
      {
        "question": "'நீங்கள் உடைத்த பானைகளைத் திருப்பித் தந்துவிட்டால், உழவரும் யானையைத் திருப்பித் தந்துவிடுவார்' - கூறியவர்?",
        "options": ["உழவர்", "மரியாதை இராமன்", "அரசர்", "அமைச்சர்"],
        "answer": 1,
        "explanation": "மரியாதை இராமன் இந்தத் தந்திரமான தீர்ப்பை வழங்கினார்."
      },
      {
        "question": "தீர்ப்பைக் கேட்ட வணிகர் என்ன கூறினார்?",
        "options": ["பானைகளைத் தருகிறேன் என்றார்", "மன்னித்து விடுங்கள், என்னால் தரமுடியாது என்றார்", "யானை வேண்டாம் என்றார்", "வழக்கை வாபஸ் பெறுவதாகக் கூறினார்"],
        "answer": 1,
        "explanation": "பழைய பானைகளைத் தர முடியாது என வணிகர் மன்னிப்புக் கேட்டார்."
      },
      {
        "question": "மரியாதை இராமன் இறுதியில் வழங்கிய தீர்ப்பு என்ன?",
        "options": ["யானைக்குப் பணம் தரவேண்டும்", "பானைக்குப் பணம் தரவேண்டும்", "யானைக்கும் பானைக்கும் சரியாகப் போய்விட்டது", "இருவருக்கும் சிறைத்தண்டனை"],
        "answer": 2,
        "explanation": "யானைக்கும் பானைக்கும் சரியாகப் போய்விட்டது என்று தீர்ப்பளித்தார்."
      },
      {
        "question": "இக்கதை உணர்த்தும் நீதி என்ன?",
        "options": ["பொறுத்தார் பூமி ஆள்வார்", "ஆத்திரக்காரனுக்குப் புத்தி மட்டு", "அறிவே ஆயுதம்", "குற்றம் பார்க்கில் சுற்றம் இல்லை"],
        "answer": 1,
        "explanation": "ஆத்திரப்படும்போது மனிதனின் புத்தி வேலை செய்யாது என்பதே இக்கதையின் நீதி."
      },
      {
        "question": "'தற்செயலாக' - இச்சொல்லின் பொருள் உணர்த்துவது எது?",
        "options": ["திட்டமிட்டு", "எதிர்பாராமல்", "கோபமாக", "வேகமாக"],
        "answer": 1,
        "explanation": "தற்செயலாக என்பது எதிர்பாராமல் நடப்பதைக் குறிக்கும்."
      },
      {
        "question": "'இரவல்' என்பதன் பொருள் என்ன?",
        "options": ["விலைக்கு வாங்குதல்", "நிரந்தரமாகப் பெறுதல்", "திருடுதல்", "திரும்பித் தரும் நிபந்தனையுடன் வாங்குதல்"],
        "answer": 3,
        "explanation": "இரவல் என்பது மீண்டும் திருப்பித் தரும் வகையில் ஒரு பொருளைப் பெறுவதாகும்."
      },
      {
        "question": "பொருத்துக: அ. வணிகர் - 1, ஆ. உழவர் - 2, இ. யானை - 3, ஈ. மரியாதை இராமன் - 4 (1. அரபு நாடு, 2. பழைய பானைகள், 3. தற்செயலாக இறந்தது, 4. விசித்திர வழக்கு)",
        "options": ["அ-1, ஆ-2, இ-3, ஈ-4", "அ-4, ஆ-3, இ-2, ஈ-1", "அ-2, ஆ-1, இ-4, ஈ-3", "அ-3, ஆ-4, இ-1, ஈ-2"],
        "answer": 0,
        "explanation": "சரியான பொருத்தம்: வணிகர் - அரபு நாடு, உழவர் - பழைய பானைகள், யானை - தற்செயலாக இறந்தது, மரியாதை இராமன் - விசித்திர வழக்கு."
      },
      {
        "question": "உழவர் பழைய பானைகளை கதவின் பின்னால் அடுக்கி வைத்ததன் காரணம்?",
        "options": ["கூற்று சரி, காரணம் தவறு", "கூற்று தவறு, காரணம் சரி", "கூற்று, காரணம் இரண்டும் சரி", "கூற்று, காரணம் இரண்டும் தவறு"],
        "answer": 2,
        "explanation": "வணிகருக்குத் தம் தவறைப் புரிய வைக்கவே இத்திட்டம் வகுக்கப்பட்டது."
      },
      {
        "question": "ஒப்புமை தருக: உழவர் : பழைய பானைகள் :: அரபு வணிகர் : ?",
        "options": ["குதிரை", "யானை", "ஒட்டகம்", "தங்கம்"],
        "answer": 1,
        "explanation": "வணிகர் இழந்தது யானையை."
      },
      {
        "question": "'காலங்காலமாக' - இச்சொல்லின் பொருள் என்ன?",
        "options": ["நேற்று", "சிறிது காலமாக", "நீண்ட காலமாக", "எதிர்காலத்தில்"],
        "answer": 2,
        "explanation": "காலங்காலமாக என்பது நீண்ட காலமாகப் போற்றி வருவதைக் குறிக்கும்."
      },
      {
        "question": "'ஆத்திரம்' என்ற சொல்லின் எதிர்ச்சொல் எது?",
        "options": ["கோபம்", "சினம்", "பொறுமை", "வேகம்"],
        "answer": 2,
        "explanation": "ஆத்திரத்தின் எதிர்ச்சொல் பொறுமை."
      },
      {
        "question": "'யானைக்கும் பானைக்கும் சரி' - இத்தொடர் எதைக் குறிக்கிறது?",
        "options": ["யானையும் பானையும் ஒன்று", "கணக்கு நேர் செய்யப்பட்டது", "பானையை விட யானை பெரியது", "யானையை பானைக்குள் வைக்கலாம்"],
        "answer": 1,
        "explanation": "இரண்டு இழப்புகளும் சமன் செய்யப்பட்டன (நியாயம் வழங்கப்பட்டது)."
      },
      {
        "question": "சொற்களை முறைப்படுத்துக: தற்செயலாக / இறந்துவிட்டது / யானை / ஊர்வலத்தில்",
        "options": ["ஊர்வலத்தில் தற்செயலாக யானை இறந்துவிட்டது", "யானை தற்செயலாக ஊர்வலத்தில் இறந்துவிட்டது", "ஊர்வலத்தில் யானை தற்செயலாக இறந்துவிட்டது", "இறந்துவிட்டது தற்செயலாக ஊர்வலத்தில் யானை"],
        "answer": 2,
        "explanation": "சரியான வாக்கிய அமைப்பு: ஊர்வலத்தில் யானை தற்செயலாக இறந்துவிட்டது."
      },
      {
        "question": "பழைமை என்பது இதன் பொருள் (கட்டத்திலிருந்து):",
        "options": ["புதிய", "பழசு", "தொன்மை", "அண்மை"],
        "answer": 2,
        "explanation": "தொன்மை என்பது பழைமையைக் குறிக்கும் சொல்."
      },
      {
        "question": "வீட்டின் முகப்பில் உள்ளது:",
        "options": ["சன்னல்", "கதவு", "மாடி", "சுவர்"],
        "answer": 1,
        "explanation": "வீட்டின் முகப்பில் கதவு இருக்கும்."
      },
      {
        "question": "வேளாண் தொழில் செய்பவர்:",
        "options": ["வணிகர்", "உழவர்", "தச்சர்", "குயவர்"],
        "answer": 1,
        "explanation": "வேளாண்மை செய்பவர் உழவர்."
      },
      {
        "question": "தும்பிக்கை உள்ள விலங்கு:",
        "options": ["சிங்கம்", "புலி", "யானை", "குதிரை"],
        "answer": 2,
        "explanation": "யானைக்குத் தும்பிக்கை உண்டு."
      },
      {
        "question": "'கூக்குரலிட்டார்' - இச்சொல்லைப் பிரித்து எழுதக் கிடைப்பது?",
        "options": ["கூ + குரலிட்டார்", "கூக்குரல் + இட்டார்", "கூக்கு + ரலிட்டார்", "கூக் + குரலிட்டார்"],
        "answer": 1,
        "explanation": "கூக்குரல் + இட்டார் = கூக்குரலிட்டார்."
      },
      {
        "question": "மரியாதை இராமன் உழவரை மட்டும் ஏன் தனியே அழைத்தார்?",
        "options": ["பரிசு கொடுக்க", "ரகசியமாகத் திட்டம் தீட்ட", "தண்டனை வழங்க", "பணம் கேட்க"],
        "answer": 1,
        "explanation": "வணிகருக்குப் பாடம் புகட்ட ஒரு திட்டத்தைக் கூறவே தனியே அழைத்தார்."
      },
      {
        "question": "'செய்வதறியாது திகைத்தார் வணிகர்' - ஏன்?",
        "options": ["யானை இறந்ததால்", "உழவர் கோபமாகக் கத்தியதைக் கண்டு", "நீதிபதி கோபப்பட்டதால்", "பானை விலை உயர்ந்தது என்பதால்"],
        "answer": 1,
        "explanation": "உழவர் உடைந்த பானைகளுக்காகச் சண்டையிட்டதைக் கண்டு திகைத்தார்."
      },
      {
        "question": "வணிகர் ஏன் இறந்துபோன அதே யானையைத் திருப்பித் தரும்படி கேட்டார்?",
        "options": ["கூற்று சரி, காரணம் சரி", "கூற்று தவறு, காரணம் சரி", "கூற்று சரி, காரணம் தவறு", "இரண்டும் தவறு"],
        "answer": 2,
        "explanation": "அவரது பிடிவாத குணமே காரணம், பணம் இல்லை என்பது காரணமல்ல."
      },
      {
        "question": "'விசித்திரமான' என்ற சொல்லுக்கு இணையான பொருள்?",
        "options": ["சாதாரணமான", "பழக்கமான", "புதுமையான/வினோதமான", "எளிமையான"],
        "answer": 2,
        "explanation": "விசித்திரம் என்பது புதுமையைக் குறிக்கும்."
      },
      {
        "question": "மரியாதை இராமன் வணிகரிடம் கேட்ட கேள்வியின் உள்நோக்கம் என்ன?",
        "options": ["உழவரைத் தண்டிப்பது", "வணிகரின் தவறைப் புரிய வைப்பது", "பானையின் விலையைக் குறைப்பது", "யானையின் மதிப்பை உயர்த்துவது"],
        "answer": 1,
        "explanation": "இறந்ததை மீட்க முடியாது என்ற உண்மையை வணிகர் உணரச் செய்தார்."
      },
      {
        "question": "பழைய பானைகள் எவ்வாறு உடைந்தன?",
        "options": ["உழவர் உடைத்தார்", "யானை மிதித்தது", "கதவு வேகமாகத் திறந்ததால் கீழே விழுந்து உடைந்தன", "நீதிபதி உடைக்கச் சொன்னார்"],
        "answer": 2,
        "explanation": "வணிகர் கதவைத் தள்ளியதால் பானைகள் கீழே விழுந்து உடைந்தன."
      },
      {
        "question": "இக்கதையில் உழவரின் பண்பு எத்தகையது?",
        "options": ["பிடிவாதக்காரர்", "பொறுப்பானவர் மற்றும் நேர்மையானவர்", "கோபக்காரர்", "ஏமாற்றுக்காரர்"],
        "answer": 1,
        "explanation": "இழப்பீடு தரத் தயாராக இருந்ததால் அவர் நேர்மையானவர்."
      },
      {
        "question": "பானைகள் உடைந்தவுடன் உழவர் ஏன் கோபப்படுவது போல் நடித்தார்?",
        "options": ["அவருக்குப் பானைகள் மிகவும் பிடிக்கும்", "நீதிபதியின் திட்டத்தை நிறைவேற்ற", "வணிகரிடம் பணம் பறிக்க", "பானைகள் விலை உயர்ந்தவை என்பதால்"],
        "answer": 1,
        "explanation": "நீதிபதி கூறிய தந்திரத்தைச் செயல்படுத்தவே அவ்வாறு நடித்தார்."
      },
      {
        "question": "மரியாதை இராமனின் தீர்ப்பு எதன் அடிப்படையில் அமைந்தது?",
        "options": ["பணத்தின் அடிப்படையில்", "உடல் வலிமை அடிப்படையில்", "அறிவுக்கூர்மை அடிப்படையில்", "பதவியின் அடிப்படையில்"],
        "answer": 2,
        "explanation": "அறிவுக்கூர்மையால் நியாயமான தீர்ப்பு வழங்கப்பட்டது."
      },
      {
        "question": "'ஆத்திரக்காரனுக்குப் புத்தி மட்டு' இதில் 'மட்டு' என்பதன் பொருள்?",
        "options": ["அதிகம்", "குறைவு", "வேகம்", "சிறப்பு"],
        "answer": 1,
        "explanation": "மட்டு என்றால் அளவு அல்லது குறைவு. கோபத்தில் அறிவு மங்கிவிடும் என்பது பொருள்."
      },
      {
        "question": "வணிகர் கதவை எவ்வாறு தட்டினார்?",
        "options": ["மெதுவாக", "ஆத்திரத்துடன்", "மகிழ்ச்சியுடன்", "அமைதியாக"],
        "answer": 1,
        "explanation": "வணிகர் ஆத்திரத்துடன் கதவைத் தள்ளினார்."
      },
      {
        "question": "மரியாதை இராமன் எந்த ஊரைச் சேர்ந்தவர் எனக் கதைகளில் கூறப்படுகிறது?",
        "options": ["மதுரை", "தெனாலிராமன் ஊர்", "தமிழகத்தின் ஒரு பகுதி (கதையின்படி பொதுவானவர்)", "அரபு நாடு"],
        "answer": 2,
        "explanation": "மரியாதை இராமன் நீதியான தீர்ப்புகளுக்குப் பெயர் பெற்ற ஒரு கற்பனை மாந்தர்."
      },
      {
        "question": "இறுதியில் வணிகர் என்ன செய்தார்?",
        "options": ["மீண்டும் வழக்குத் தொடர்ந்தார்", "மன்னிப்புக் கேட்டு யானையை விட்டுக்கொடுத்தார்", "பானைகளைத் தந்தார்", "ஊரை விட்டு ஓடினார்"],
        "answer": 1,
        "explanation": "தம் பிடிவாதத்தின் தவறை உணர்ந்து மன்னிப்புக் கோரினார்."
      }
    ]
  }
}
